{"objectIdFieldName":"OBJECTID","uniqueIdField":{"name":"OBJECTID","isSystemMaintained":true,"additionalProperties":{}},"globalIdFieldName":"","geometryType":"esriGeometryPolygon","spatialReference":{"wkid":4326,"latestWkid":4326,"additionalProperties":{}},"fields":[{"name":"OBJECTID","type":"esriFieldTypeOID","alias":"OBJECTID","sqlType":"sqlTypeOther","length":null,"domain":null,"defaultValue":null,"additionalProperties":{}},{"name":"ADE","type":"esriFieldTypeSmallInteger","alias":"ADE","sqlType":"sqlTypeOther","length":null,"domain":null,"defaultValue":null,"additionalProperties":{}},{"name":"GF","type":"esriFieldTypeSmallInteger","alias":"GF","sqlType":"sqlTypeOther","length":null,"domain":null,"defaultValue":null,"additionalProperties":{}},{"name":"BSG","type":"esriFieldTypeSmallInteger","alias":"BSG","sqlType":"sqlTypeOther","length":null,"domain":null,"defaultValue":null,"additionalProperties":{}},{"name":"RS","type":"esriFieldTypeString","alias":"RS","sqlType":"sqlTypeOther","length":5,"domain":null,"defaultValue":null,"additionalProperties":{}},{"name":"AGS","type":"esriFieldTypeString","alias":"AGS","sqlType":"sqlTypeOther","length":5,"domain":null,"defaultValue":null,"additionalProperties":{}},{"name":"SDV_RS","type":"esriFieldTypeString","alias":"SDV_RS","sqlType":"sqlTypeOther","length":12,"domain":null,"defaultValue":null,"additionalProperties":{}},{"name":"GEN","type":"esriFieldTypeString","alias":"GEN","sqlType":"sqlTypeOther","length":33,"domain":null,"defaultValue":null,"additionalProperties":{}},{"name":"BEZ","type":"esriFieldTypeString","alias":"BEZ","sqlType":"sqlTypeOther","length":16,"domain":null,"defaultValue":null,"additionalProperties":{}},{"name":"IBZ","type":"esriFieldTypeSmallInteger","alias":"IBZ","sqlType":"sqlTypeOther","length":null,"domain":null,"defaultValue":null,"additionalProperties":{}},{"name":"BEM","type":"esriFieldTypeString","alias":"BEM","sqlType":"sqlTypeOther","length":13,"domain":null,"defaultValue":null,"additionalProperties":{}},{"name":"NBD","type":"esriFieldTypeString","alias":"NBD","sqlType":"sqlTypeOther","length":4,"domain":null,"defaultValue":null,"additionalProperties":{}},{"name":"SN_L","type":"esriFieldTypeString","alias":"SN_L","sqlType":"sqlTypeOther","length":2,"domain":null,"defaultValue":null,"additionalProperties":{}},{"name":"SN_R","type":"esriFieldTypeString","alias":"SN_R","sqlType":"sqlTypeOther","length":1,"domain":null,"defaultValue":null,"additionalProperties":{}},{"name":"SN_K","type":"esriFieldTypeString","alias":"SN_K","sqlType":"sqlTypeOther","length":2,"domain":null,"defaultValue":null,"additionalProperties":{}},{"name":"SN_V1","type":"esriFieldTypeString","alias":"SN_V1","sqlType":"sqlTypeOther","length":2,"domain":null,"defaultValue":null,"additionalProperties":{}},{"name":"SN_V2","type":"esriFieldTypeString","alias":"SN_V2","sqlType":"sqlTypeOther","length":2,"domain":null,"defaultValue":null,"additionalProperties":{}},{"name":"SN_G","type":"esriFieldTypeString","alias":"SN_G","sqlType":"sqlTypeOther","length":3,"domain":null,"defaultValue":null,"additionalProperties":{}},{"name":"FK_S3","type":"esriFieldTypeString","alias":"FK_S3","sqlType":"sqlTypeOther","length":1,"domain":null,"defaultValue":null,"additionalProperties":{}},{"name":"NUTS","type":"esriFieldTypeString","alias":"NUTS","sqlType":"sqlTypeOther","length":5,"domain":null,"defaultValue":null,"additionalProperties":{}},{"name":"RS_0","type":"esriFieldTypeString","alias":"RS_0","sqlType":"sqlTypeOther","length":12,"domain":null,"defaultValue":null,"additionalProperties":{}},{"name":"AGS_0","type":"esriFieldTypeString","alias":"AGS_0","sqlType":"sqlTypeOther","length":8,"domain":null,"defaultValue":null,"additionalProperties":{}},{"name":"WSK","type":"esriFieldTypeString","alias":"WSK","sqlType":"sqlTypeOther","length":23,"domain":null,"defaultValue":null,"additionalProperties":{}},{"name":"EWZ","type":"esriFieldTypeInteger","alias":"Einwohnerzahl","sqlType":"sqlTypeOther","length":null,"domain":null,"defaultValue":null,"additionalProperties":{}},{"name":"KFL","type":"esriFieldTypeDouble","alias":"KFL","sqlType":"sqlTypeOther","length":null,"domain":null,"defaultValue":null,"additionalProperties":{}},{"name":"DEBKG_ID","type":"esriFieldTypeString","alias":"DEBKG_ID","sqlType":"sqlTypeOther","length":16,"domain":null,"defaultValue":null,"additionalProperties":{}},{"name":"Shape__Area","type":"esriFieldTypeDouble","alias":"Shape__Area","sqlType":"sqlTypeDouble","length":null,"domain":null,"defaultValue":null,"additionalProperties":{}},{"name":"Shape__Length","type":"esriFieldTypeDouble","alias":"Shape__Length","sqlType":"sqlTypeDouble","length":null,"domain":null,"defaultValue":null,"additionalProperties":{}},{"name":"death_rate","type":"esriFieldTypeDouble","alias":"Sterberate","sqlType":"sqlTypeOther","length":null,"domain":null,"defaultValue":null,"additionalProperties":{}},{"name":"cases","type":"esriFieldTypeInteger","alias":"Fälle","sqlType":"sqlTypeOther","length":null,"domain":null,"defaultValue":null,"additionalProperties":{}},{"name":"deaths","type":"esriFieldTypeInteger","alias":"Todesfälle","sqlType":"sqlTypeOther","length":null,"domain":null,"defaultValue":null,"additionalProperties":{}},{"name":"cases_per_100k","type":"esriFieldTypeDouble","alias":"Fälle/100.000 EW","sqlType":"sqlTypeOther","length":null,"domain":null,"defaultValue":null,"additionalProperties":{}},{"name":"cases_per_population","type":"esriFieldTypeDouble","alias":"Betroffenenrate %","sqlType":"sqlTypeOther","length":null,"domain":null,"defaultValue":null,"additionalProperties":{}},{"name":"BL","type":"esriFieldTypeString","alias":"Bundesland","sqlType":"sqlTypeOther","length":256,"domain":null,"defaultValue":null,"additionalProperties":{}},{"name":"BL_ID","type":"esriFieldTypeString","alias":"Bundesland ID","sqlType":"sqlTypeOther","length":256,"domain":null,"defaultValue":null,"additionalProperties":{}},{"name":"county","type":"esriFieldTypeString","alias":"Landkreis","sqlType":"sqlTypeOther","length":256,"domain":null,"defaultValue":null,"additionalProperties":{}},{"name":"last_update","type":"esriFieldTypeString","alias":"Aktualisierung","sqlType":"sqlTypeOther","length":256,"domain":null,"defaultValue":null,"additionalProperties":{}},{"name":"cases7_per_100k","type":"esriFieldTypeDouble","alias":"Fälle letzte 7 Tage/100.000 EW","sqlType":"sqlTypeOther","length":null,"domain":null,"defaultValue":null,"additionalProperties":{}},{"name":"recovered","type":"esriFieldTypeInteger","alias":"Genesene","sqlType":"sqlTypeOther","length":null,"domain":null,"defaultValue":null,"additionalProperties":{}},{"name":"EWZ_BL","type":"esriFieldTypeInteger","alias":"EWZ_BL","sqlType":"sqlTypeOther","length":null,"domain":null,"defaultValue":null,"additionalProperties":{}},{"name":"cases7_bl_per_100k","type":"esriFieldTypeDouble","alias":"Bundeslandweite Fälle der letzten 7 Tage/100.000 EW","sqlType":"sqlTypeOther","length":null,"domain":null,"defaultValue":null,"additionalProperties":{}},{"name":"cases7_bl","type":"esriFieldTypeInteger","alias":"Fälle der letzten 7 Tage pro Bundesland","sqlType":"sqlTypeOther","length":null,"domain":null,"defaultValue":null,"additionalProperties":{}},{"name":"death7_bl","type":"esriFieldTypeInteger","alias":"Todesfälle der letzten 7 Tage pro Bundesland","sqlType":"sqlTypeOther","length":null,"domain":null,"defaultValue":null,"additionalProperties":{}},{"name":"cases7_lk","type":"esriFieldTypeInteger","alias":"Fälle der letzten 7 Tage pro Landkreis","sqlType":"sqlTypeOther","length":null,"domain":null,"defaultValue":null,"additionalProperties":{}},{"name":"death7_lk","type":"esriFieldTypeInteger","alias":"Todesfälle der letzten 7 Tage pro Landkreis","sqlType":"sqlTypeOther","length":null,"domain":null,"defaultValue":null,"additionalProperties":{}},{"name":"cases7_per_100k_txt","type":"esriFieldTypeString","alias":"Fälle der letzten 7 Tage/100000 EW (Text)","sqlType":"sqlTypeOther","length":256,"domain":null,"defaultValue":null,"additionalProperties":{}},{"name":"AdmUnitId","type":"esriFieldTypeInteger","alias":"AdmUnitId","sqlType":"sqlTypeInteger","length":null,"domain":null,"defaultValue":null,"additionalProperties":{}}],"features":[{"attributes":{"cases7_Per_100k":1653.43474103231,"last_Update":"10.03.2022, 00:00 Uhr","additionalProperties":{},"sn_V2":"00","gen":"Flensburg","ags":"01001"}},{"attributes":{"cases7_Per_100k":1118.00033252096,"last_Update":"10.03.2022, 00:00 Uhr","additionalProperties":{},"sn_V2":"00","gen":"Kiel","ags":"01002"}},{"attributes":{"cases7_Per_100k":911.297869777527,"last_Update":"10.03.2022, 00:00 Uhr","additionalProperties":{},"sn_V2":"00","gen":"Lübeck","ags":"01003"}},{"attributes":{"cases7_Per_100k":1047.49389900507,"last_Update":"10.03.2022, 00:00 Uhr","additionalProperties":{},"sn_V2":"00","gen":"Neumünster","ags":"01004"}},{"attributes":{"cases7_Per_100k":1527.19304170325,"last_Update":"10.03.2022, 00:00 Uhr","additionalProperties":{},"sn_V2":"00","gen":"Dithmarschen","ags":"01051"}},{"attributes":{"cases7_Per_100k":784.325540290833,"last_Update":"10.03.2022, 00:00 Uhr","additionalProperties":{},"sn_V2":"00","gen":"Herzogtum Lauenburg","ags":"01053"}},{"attributes":{"cases7_Per_100k":1638.67733192938,"last_Update":"10.03.2022, 00:00 Uhr","additionalProperties":{},"sn_V2":"00","gen":"Nordfriesland","ags":"01054"}},{"attributes":{"cases7_Per_100k":835.289621662936,"last_Update":"10.03.2022, 00:00 Uhr","additionalProperties":{},"sn_V2":"00","gen":"Ostholstein","ags":"01055"}},{"attributes":{"cases7_Per_100k":717.473232729394,"last_Update":"10.03.2022, 00:00 Uhr","additionalProperties":{},"sn_V2":"00","gen":"Pinneberg","ags":"01056"}},{"attributes":{"cases7_Per_100k":986.447937040502,"last_Update":"10.03.2022, 00:00 Uhr","additionalProperties":{},"sn_V2":"00","gen":"Plön","ags":"01057"}},{"attributes":{"cases7_Per_100k":1276.36343784689,"last_Update":"10.03.2022, 00:00 Uhr","additionalProperties":{},"sn_V2":"00","gen":"Rendsburg-Eckernförde","ags":"01058"}},{"attributes":{"cases7_Per_100k":1364.93508416113,"last_Update":"10.03.2022, 00:00 Uhr","additionalProperties":{},"sn_V2":"00","gen":"Schleswig-Flensburg","ags":"01059"}},{"attributes":{"cases7_Per_100k":1044.93771739561,"last_Update":"10.03.2022, 00:00 Uhr","additionalProperties":{},"sn_V2":"00","gen":"Segeberg","ags":"01060"}},{"attributes":{"cases7_Per_100k":988.477958165654,"last_Update":"10.03.2022, 00:00 Uhr","additionalProperties":{},"sn_V2":"00","gen":"Steinburg","ags":"01061"}},{"attributes":{"cases7_Per_100k":802.893191122867,"last_Update":"10.03.2022, 00:00 Uhr","additionalProperties":{},"sn_V2":"00","gen":"Stormarn","ags":"01062"}},{"attributes":{"cases7_Per_100k":604.59557414447,"last_Update":"10.03.2022, 00:00 Uhr","additionalProperties":{},"sn_V2":"00","gen":"Hamburg","ags":"02000"}},{"attributes":{"cases7_Per_100k":1303.10064732601,"last_Update":"10.03.2022, 00:00 Uhr","additionalProperties":{},"sn_V2":"00","gen":"Braunschweig","ags":"03101"}},{"attributes":{"cases7_Per_100k":1645.38925153563,"last_Update":"10.03.2022, 00:00 Uhr","additionalProperties":{},"sn_V2":"00","gen":"Salzgitter","ags":"03102"}},{"attributes":{"cases7_Per_100k":1153.1007751938,"last_Update":"10.03.2022, 00:00 Uhr","additionalProperties":{},"sn_V2":"00","gen":"Wolfsburg","ags":"03103"}},{"attributes":{"cases7_Per_100k":1462.53110417713,"last_Update":"10.03.2022, 00:00 Uhr","additionalProperties":{},"sn_V2":"00","gen":"Gifhorn","ags":"03151"}},{"attributes":{"cases7_Per_100k":1423.28937990021,"last_Update":"10.03.2022, 00:00 Uhr","additionalProperties":{},"sn_V2":"00","gen":"Goslar","ags":"03153"}},{"attributes":{"cases7_Per_100k":871.959614502065,"last_Update":"10.03.2022, 00:00 Uhr","additionalProperties":{},"sn_V2":"00","gen":"Helmstedt","ags":"03154"}},{"attributes":{"cases7_Per_100k":1744.68020520293,"last_Update":"10.03.2022, 00:00 Uhr","additionalProperties":{},"sn_V2":"00","gen":"Northeim","ags":"03155"}},{"attributes":{"cases7_Per_100k":1649.68640499396,"last_Update":"10.03.2022, 00:00 Uhr","additionalProperties":{},"sn_V2":"00","gen":"Peine","ags":"03157"}},{"attributes":{"cases7_Per_100k":1486.24760181299,"last_Update":"10.03.2022, 00:00 Uhr","additionalProperties":{},"sn_V2":"00","gen":"Wolfenbüttel","ags":"03158"}},{"attributes":{"cases7_Per_100k":1034.26983636925,"last_Update":"10.03.2022, 00:00 Uhr","additionalProperties":{},"sn_V2":"00","gen":"Göttingen","ags":"03159"}},{"attributes":{"cases7_Per_100k":1355.28377173621,"last_Update":"10.03.2022, 00:00 Uhr","additionalProperties":{},"sn_V2":"00","gen":"Region Hannover","ags":"03241"}},{"attributes":{"cases7_Per_100k":1052.40471037089,"last_Update":"10.03.2022, 00:00 Uhr","additionalProperties":{},"sn_V2":"00","gen":"Diepholz","ags":"03251"}},{"attributes":{"cases7_Per_100k":1633.4634540315,"last_Update":"10.03.2022, 00:00 Uhr","additionalProperties":{},"sn_V2":"00","gen":"Hameln-Pyrmont","ags":"03252"}},{"attributes":{"cases7_Per_100k":1529.05642842622,"last_Update":"10.03.2022, 00:00 Uhr","additionalProperties":{},"sn_V2":"00","gen":"Hildesheim","ags":"03254"}},{"attributes":{"cases7_Per_100k":1367.38501858789,"last_Update":"10.03.2022, 00:00 Uhr","additionalProperties":{},"sn_V2":"00","gen":"Holzminden","ags":"03255"}},{"attributes":{"cases7_Per_100k":1219.12121336676,"last_Update":"10.03.2022, 00:00 Uhr","additionalProperties":{},"sn_V2":"00","gen":"Nienburg (Weser)","ags":"03256"}},{"attributes":{"cases7_Per_100k":1708.2686261884,"last_Update":"10.03.2022, 00:00 Uhr","additionalProperties":{},"sn_V2":"00","gen":"Schaumburg","ags":"03257"}},{"attributes":{"cases7_Per_100k":1077.56458140546,"last_Update":"10.03.2022, 00:00 Uhr","additionalProperties":{},"sn_V2":"00","gen":"Celle","ags":"03351"}},{"attributes":{"cases7_Per_100k":1075.81503425105,"last_Update":"10.03.2022, 00:00 Uhr","additionalProperties":{},"sn_V2":"00","gen":"Cuxhaven","ags":"03352"}},{"attributes":{"cases7_Per_100k":992.906693331667,"last_Update":"10.03.2022, 00:00 Uhr","additionalProperties":{},"sn_V2":"00","gen":"Harburg","ags":"03353"}},{"attributes":{"cases7_Per_100k":1129.82702100901,"last_Update":"10.03.2022, 00:00 Uhr","additionalProperties":{},"sn_V2":"00","gen":"Lüchow-Dannenberg","ags":"03354"}},{"attributes":{"cases7_Per_100k":1171.87287974598,"last_Update":"10.03.2022, 00:00 Uhr","additionalProperties":{},"sn_V2":"00","gen":"Lüneburg","ags":"03355"}},{"attributes":{"cases7_Per_100k":971.737613398465,"last_Update":"10.03.2022, 00:00 Uhr","additionalProperties":{},"sn_V2":"00","gen":"Osterholz","ags":"03356"}},{"attributes":{"cases7_Per_100k":887.005581022093,"last_Update":"10.03.2022, 00:00 Uhr","additionalProperties":{},"sn_V2":"00","gen":"Rotenburg (Wümme)","ags":"03357"}},{"attributes":{"cases7_Per_100k":1134.2584377329,"last_Update":"10.03.2022, 00:00 Uhr","additionalProperties":{},"sn_V2":"00","gen":"Heidekreis","ags":"03358"}},{"attributes":{"cases7_Per_100k":926.67890551576,"last_Update":"10.03.2022, 00:00 Uhr","additionalProperties":{},"sn_V2":"00","gen":"Stade","ags":"03359"}},{"attributes":{"cases7_Per_100k":839.401075989024,"last_Update":"10.03.2022, 00:00 Uhr","additionalProperties":{},"sn_V2":"00","gen":"Uelzen","ags":"03360"}},{"attributes":{"cases7_Per_100k":861.354616424615,"last_Update":"10.03.2022, 00:00 Uhr","additionalProperties":{},"sn_V2":"00","gen":"Verden","ags":"03361"}},{"attributes":{"cases7_Per_100k":825.774486148923,"last_Update":"10.03.2022, 00:00 Uhr","additionalProperties":{},"sn_V2":"00","gen":"Delmenhorst","ags":"03401"}},{"attributes":{"cases7_Per_100k":1405.5419657537,"last_Update":"10.03.2022, 00:00 Uhr","additionalProperties":{},"sn_V2":"00","gen":"Emden","ags":"03402"}},{"attributes":{"cases7_Per_100k":826.036968249757,"last_Update":"10.03.2022, 00:00 Uhr","additionalProperties":{},"sn_V2":"00","gen":"Oldenburg (Oldb)","ags":"03403"}},{"attributes":{"cases7_Per_100k":1277.53116189572,"last_Update":"10.03.2022, 00:00 Uhr","additionalProperties":{},"sn_V2":"00","gen":"Osnabrück","ags":"03404"}},{"attributes":{"cases7_Per_100k":763.409541289284,"last_Update":"10.03.2022, 00:00 Uhr","additionalProperties":{},"sn_V2":"00","gen":"Wilhelmshaven","ags":"03405"}},{"attributes":{"cases7_Per_100k":917.679456873841,"last_Update":"10.03.2022, 00:00 Uhr","additionalProperties":{},"sn_V2":"00","gen":"Ammerland","ags":"03451"}},{"attributes":{"cases7_Per_100k":1038.50077296007,"last_Update":"10.03.2022, 00:00 Uhr","additionalProperties":{},"sn_V2":"00","gen":"Aurich","ags":"03452"}},{"attributes":{"cases7_Per_100k":1211.24704573891,"last_Update":"10.03.2022, 00:00 Uhr","additionalProperties":{},"sn_V2":"00","gen":"Cloppenburg","ags":"03453"}},{"attributes":{"cases7_Per_100k":1676.34451099018,"last_Update":"10.03.2022, 00:00 Uhr","additionalProperties":{},"sn_V2":"00","gen":"Emsland","ags":"03454"}},{"attributes":{"cases7_Per_100k":977.053884471209,"last_Update":"10.03.2022, 00:00 Uhr","additionalProperties":{},"sn_V2":"00","gen":"Friesland","ags":"03455"}},{"attributes":{"cases7_Per_100k":2673.12587478516,"last_Update":"10.03.2022, 00:00 Uhr","additionalProperties":{},"sn_V2":"00","gen":"Grafschaft Bentheim","ags":"03456"}},{"attributes":{"cases7_Per_100k":1431.62879119213,"last_Update":"10.03.2022, 00:00 Uhr","additionalProperties":{},"sn_V2":"00","gen":"Leer","ags":"03457"}},{"attributes":{"cases7_Per_100k":962.218655632212,"last_Update":"10.03.2022, 00:00 Uhr","additionalProperties":{},"sn_V2":"00","gen":"Oldenburg","ags":"03458"}},{"attributes":{"cases7_Per_100k":1405.95486144919,"last_Update":"10.03.2022, 00:00 Uhr","additionalProperties":{},"sn_V2":"00","gen":"Osnabrück","ags":"03459"}},{"attributes":{"cases7_Per_100k":1058.4698464836,"last_Update":"10.03.2022, 00:00 Uhr","additionalProperties":{},"sn_V2":"00","gen":"Vechta","ags":"03460"}},{"attributes":{"cases7_Per_100k":703.763951018933,"last_Update":"10.03.2022, 00:00 Uhr","additionalProperties":{},"sn_V2":"00","gen":"Wesermarsch","ags":"03461"}},{"attributes":{"cases7_Per_100k":1733.93280356894,"last_Update":"10.03.2022, 00:00 Uhr","additionalProperties":{},"sn_V2":"00","gen":"Wittmund","ags":"03462"}},{"attributes":{"cases7_Per_100k":729.650018620725,"last_Update":"10.03.2022, 00:00 Uhr","additionalProperties":{},"sn_V2":"00","gen":"Bremen","ags":"04011"}},{"attributes":{"cases7_Per_100k":1039.12572540662,"last_Update":"10.03.2022, 00:00 Uhr","additionalProperties":{},"sn_V2":"00","gen":"Bremerhaven","ags":"04012"}},{"attributes":{"cases7_Per_100k":1223.96752416913,"last_Update":"10.03.2022, 00:00 Uhr","additionalProperties":{},"sn_V2":"00","gen":"Düsseldorf","ags":"05111"}},{"attributes":{"cases7_Per_100k":701.372293979451,"last_Update":"10.03.2022, 00:00 Uhr","additionalProperties":{},"sn_V2":"00","gen":"Duisburg","ags":"05112"}},{"attributes":{"cases7_Per_100k":720.276778585716,"last_Update":"10.03.2022, 00:00 Uhr","additionalProperties":{},"sn_V2":"00","gen":"Essen","ags":"05113"}},{"attributes":{"cases7_Per_100k":1096.78898273704,"last_Update":"10.03.2022, 00:00 Uhr","additionalProperties":{},"sn_V2":"00","gen":"Krefeld","ags":"05114"}},{"attributes":{"cases7_Per_100k":923.112471838715,"last_Update":"10.03.2022, 00:00 Uhr","additionalProperties":{},"sn_V2":"00","gen":"Mönchengladbach","ags":"05116"}},{"attributes":{"cases7_Per_100k":870.577635281797,"last_Update":"10.03.2022, 00:00 Uhr","additionalProperties":{},"sn_V2":"00","gen":"Mülheim an der Ruhr","ags":"05117"}},{"attributes":{"cases7_Per_100k":662.798354694941,"last_Update":"10.03.2022, 00:00 Uhr","additionalProperties":{},"sn_V2":"00","gen":"Oberhausen","ags":"05119"}},{"attributes":{"cases7_Per_100k":1225.83306431364,"last_Update":"10.03.2022, 00:00 Uhr","additionalProperties":{},"sn_V2":"00","gen":"Remscheid","ags":"05120"}},{"attributes":{"cases7_Per_100k":1451.06882840326,"last_Update":"10.03.2022, 00:00 Uhr","additionalProperties":{},"sn_V2":"00","gen":"Solingen","ags":"05122"}},{"attributes":{"cases7_Per_100k":1363.6466067988,"last_Update":"10.03.2022, 00:00 Uhr","additionalProperties":{},"sn_V2":"00","gen":"Wuppertal","ags":"05124"}},{"attributes":{"cases7_Per_100k":1183.08853073798,"last_Update":"10.03.2022, 00:00 Uhr","additionalProperties":{},"sn_V2":"00","gen":"Kleve","ags":"05154"}},{"attributes":{"cases7_Per_100k":1154.60375535284,"last_Update":"10.03.2022, 00:00 Uhr","additionalProperties":{},"sn_V2":"00","gen":"Mettmann","ags":"05158"}},{"attributes":{"cases7_Per_100k":1299.11217010582,"last_Update":"10.03.2022, 00:00 Uhr","additionalProperties":{},"sn_V2":"00","gen":"Rhein-Kreis Neuss","ags":"05162"}},{"attributes":{"cases7_Per_100k":1371.6938660664,"last_Update":"10.03.2022, 00:00 Uhr","additionalProperties":{},"sn_V2":"00","gen":"Viersen","ags":"05166"}},{"attributes":{"cases7_Per_100k":1111.68343428679,"last_Update":"10.03.2022, 00:00 Uhr","additionalProperties":{},"sn_V2":"00","gen":"Wesel","ags":"05170"}},{"attributes":{"cases7_Per_100k":1806.52733537218,"last_Update":"10.03.2022, 00:00 Uhr","additionalProperties":{},"sn_V2":"00","gen":"Bonn","ags":"05314"}},{"attributes":{"cases7_Per_100k":2784.59212661214,"last_Update":"10.03.2022, 00:00 Uhr","additionalProperties":{},"sn_V2":"00","gen":"Köln","ags":"05315"}},{"attributes":{"cases7_Per_100k":1802.26350629938,"last_Update":"10.03.2022, 00:00 Uhr","additionalProperties":{},"sn_V2":"00","gen":"Leverkusen","ags":"05316"}},{"attributes":{"cases7_Per_100k":1407.21591143864,"last_Update":"10.03.2022, 00:00 Uhr","additionalProperties":{},"sn_V2":"00","gen":"Städteregion Aachen","ags":"05334"}},{"attributes":{"cases7_Per_100k":2165.27117749114,"last_Update":"10.03.2022, 00:00 Uhr","additionalProperties":{},"sn_V2":"00","gen":"Düren","ags":"05358"}},{"attributes":{"cases7_Per_100k":2116.64547891766,"last_Update":"10.03.2022, 00:00 Uhr","additionalProperties":{},"sn_V2":"00","gen":"Rhein-Erft-Kreis","ags":"05362"}},{"attributes":{"cases7_Per_100k":2302.95484129883,"last_Update":"10.03.2022, 00:00 Uhr","additionalProperties":{},"sn_V2":"00","gen":"Euskirchen","ags":"05366"}},{"attributes":{"cases7_Per_100k":1083.99815954269,"last_Update":"10.03.2022, 00:00 Uhr","additionalProperties":{},"sn_V2":"00","gen":"Heinsberg","ags":"05370"}},{"attributes":{"cases7_Per_100k":1617.9669413579,"last_Update":"10.03.2022, 00:00 Uhr","additionalProperties":{},"sn_V2":"00","gen":"Oberbergischer Kreis","ags":"05374"}},{"attributes":{"cases7_Per_100k":1505.60409496073,"last_Update":"10.03.2022, 00:00 Uhr","additionalProperties":{},"sn_V2":"00","gen":"Rheinisch-Bergischer Kreis","ags":"05378"}},{"attributes":{"cases7_Per_100k":1274.37018530085,"last_Update":"10.03.2022, 00:00 Uhr","additionalProperties":{},"sn_V2":"00","gen":"Rhein-Sieg-Kreis","ags":"05382"}},{"attributes":{"cases7_Per_100k":891.062118785566,"last_Update":"10.03.2022, 00:00 Uhr","additionalProperties":{},"sn_V2":"00","gen":"Bottrop","ags":"05512"}},{"attributes":{"cases7_Per_100k":822.832442446113,"last_Update":"10.03.2022, 00:00 Uhr","additionalProperties":{},"sn_V2":"00","gen":"Gelsenkirchen","ags":"05513"}},{"attributes":{"cases7_Per_100k":1344.80393675155,"last_Update":"10.03.2022, 00:00 Uhr","additionalProperties":{},"sn_V2":"00","gen":"Münster","ags":"05515"}},{"attributes":{"cases7_Per_100k":2050.29336000731,"last_Update":"10.03.2022, 00:00 Uhr","additionalProperties":{},"sn_V2":"00","gen":"Borken","ags":"05554"}},{"attributes":{"cases7_Per_100k":1730.3091811954,"last_Update":"10.03.2022, 00:00 Uhr","additionalProperties":{},"sn_V2":"00","gen":"Coesfeld","ags":"05558"}},{"attributes":{"cases7_Per_100k":947.198414599763,"last_Update":"10.03.2022, 00:00 Uhr","additionalProperties":{},"sn_V2":"00","gen":"Recklinghausen","ags":"05562"}},{"attributes":{"cases7_Per_100k":1261.49884983612,"last_Update":"10.03.2022, 00:00 Uhr","additionalProperties":{},"sn_V2":"00","gen":"Steinfurt","ags":"05566"}},{"attributes":{"cases7_Per_100k":1427.45397722562,"last_Update":"10.03.2022, 00:00 Uhr","additionalProperties":{},"sn_V2":"00","gen":"Warendorf","ags":"05570"}},{"attributes":{"cases7_Per_100k":1271.92969305176,"last_Update":"10.03.2022, 00:00 Uhr","additionalProperties":{},"sn_V2":"00","gen":"Bielefeld","ags":"05711"}},{"attributes":{"cases7_Per_100k":1444.8300248343,"last_Update":"10.03.2022, 00:00 Uhr","additionalProperties":{},"sn_V2":"00","gen":"Gütersloh","ags":"05754"}},{"attributes":{"cases7_Per_100k":1428.47449779882,"last_Update":"10.03.2022, 00:00 Uhr","additionalProperties":{},"sn_V2":"00","gen":"Herford","ags":"05758"}},{"attributes":{"cases7_Per_100k":1666.79787302564,"last_Update":"10.03.2022, 00:00 Uhr","additionalProperties":{},"sn_V2":"00","gen":"Höxter","ags":"05762"}},{"attributes":{"cases7_Per_100k":1300.11240164856,"last_Update":"10.03.2022, 00:00 Uhr","additionalProperties":{},"sn_V2":"00","gen":"Lippe","ags":"05766"}},{"attributes":{"cases7_Per_100k":1510.61978276985,"last_Update":"10.03.2022, 00:00 Uhr","additionalProperties":{},"sn_V2":"00","gen":"Minden-Lübbecke","ags":"05770"}},{"attributes":{"cases7_Per_100k":1059.23751763504,"last_Update":"10.03.2022, 00:00 Uhr","additionalProperties":{},"sn_V2":"00","gen":"Paderborn","ags":"05774"}},{"attributes":{"cases7_Per_100k":893.665592914332,"last_Update":"10.03.2022, 00:00 Uhr","additionalProperties":{},"sn_V2":"00","gen":"Bochum","ags":"05911"}},{"attributes":{"cases7_Per_100k":990.307914295826,"last_Update":"10.03.2022, 00:00 Uhr","additionalProperties":{},"sn_V2":"00","gen":"Dortmund","ags":"05913"}},{"attributes":{"cases7_Per_100k":847.965148632391,"last_Update":"10.03.2022, 00:00 Uhr","additionalProperties":{},"sn_V2":"00","gen":"Hagen","ags":"05914"}},{"attributes":{"cases7_Per_100k":1078.96986595294,"last_Update":"10.03.2022, 00:00 Uhr","additionalProperties":{},"sn_V2":"00","gen":"Hamm","ags":"05915"}},{"attributes":{"cases7_Per_100k":986.364215623805,"last_Update":"10.03.2022, 00:00 Uhr","additionalProperties":{},"sn_V2":"00","gen":"Herne","ags":"05916"}},{"attributes":{"cases7_Per_100k":883.235849348559,"last_Update":"10.03.2022, 00:00 Uhr","additionalProperties":{},"sn_V2":"00","gen":"Ennepe-Ruhr-Kreis","ags":"05954"}},{"attributes":{"cases7_Per_100k":1621.04775508628,"last_Update":"10.03.2022, 00:00 Uhr","additionalProperties":{},"sn_V2":"00","gen":"Hochsauerlandkreis","ags":"05958"}},{"attributes":{"cases7_Per_100k":1155.72282228345,"last_Update":"10.03.2022, 00:00 Uhr","additionalProperties":{},"sn_V2":"00","gen":"Märkischer Kreis","ags":"05962"}},{"attributes":{"cases7_Per_100k":1538.66918612498,"last_Update":"10.03.2022, 00:00 Uhr","additionalProperties":{},"sn_V2":"00","gen":"Olpe","ags":"05966"}},{"attributes":{"cases7_Per_100k":1084.97192285773,"last_Update":"10.03.2022, 00:00 Uhr","additionalProperties":{},"sn_V2":"00","gen":"Siegen-Wittgenstein","ags":"05970"}},{"attributes":{"cases7_Per_100k":1485.96752332102,"last_Update":"10.03.2022, 00:00 Uhr","additionalProperties":{},"sn_V2":"00","gen":"Soest","ags":"05974"}},{"attributes":{"cases7_Per_100k":409.534116834088,"last_Update":"10.03.2022, 00:00 Uhr","additionalProperties":{},"sn_V2":"00","gen":"Unna","ags":"05978"}},{"attributes":{"cases7_Per_100k":796.612512093684,"last_Update":"10.03.2022, 00:00 Uhr","additionalProperties":{},"sn_V2":"00","gen":"Darmstadt","ags":"06411"}},{"attributes":{"cases7_Per_100k":844.649419450755,"last_Update":"10.03.2022, 00:00 Uhr","additionalProperties":{},"sn_V2":"00","gen":"Frankfurt am Main","ags":"06412"}},{"attributes":{"cases7_Per_100k":825.87171102894,"last_Update":"10.03.2022, 00:00 Uhr","additionalProperties":{},"sn_V2":"00","gen":"Offenbach am Main","ags":"06413"}},{"attributes":{"cases7_Per_100k":1203.83763625726,"last_Update":"10.03.2022, 00:00 Uhr","additionalProperties":{},"sn_V2":"00","gen":"Wiesbaden","ags":"06414"}},{"attributes":{"cases7_Per_100k":1453.79407043891,"last_Update":"10.03.2022, 00:00 Uhr","additionalProperties":{},"sn_V2":"00","gen":"Bergstraße","ags":"06431"}},{"attributes":{"cases7_Per_100k":996.637565879859,"last_Update":"10.03.2022, 00:00 Uhr","additionalProperties":{},"sn_V2":"00","gen":"Darmstadt-Dieburg","ags":"06432"}},{"attributes":{"cases7_Per_100k":920.571269039582,"last_Update":"10.03.2022, 00:00 Uhr","additionalProperties":{},"sn_V2":"00","gen":"Groß-Gerau","ags":"06433"}},{"attributes":{"cases7_Per_100k":1015.25195864819,"last_Update":"10.03.2022, 00:00 Uhr","additionalProperties":{},"sn_V2":"00","gen":"Hochtaunuskreis","ags":"06434"}},{"attributes":{"cases7_Per_100k":1162.94235799369,"last_Update":"10.03.2022, 00:00 Uhr","additionalProperties":{},"sn_V2":"00","gen":"Main-Kinzig-Kreis","ags":"06435"}},{"attributes":{"cases7_Per_100k":863.063394409523,"last_Update":"10.03.2022, 00:00 Uhr","additionalProperties":{},"sn_V2":"00","gen":"Main-Taunus-Kreis","ags":"06436"}},{"attributes":{"cases7_Per_100k":1320.87562271327,"last_Update":"10.03.2022, 00:00 Uhr","additionalProperties":{},"sn_V2":"00","gen":"Odenwaldkreis","ags":"06437"}},{"attributes":{"cases7_Per_100k":1128.61878824935,"last_Update":"10.03.2022, 00:00 Uhr","additionalProperties":{},"sn_V2":"00","gen":"Offenbach","ags":"06438"}},{"attributes":{"cases7_Per_100k":1196.16076144542,"last_Update":"10.03.2022, 00:00 Uhr","additionalProperties":{},"sn_V2":"00","gen":"Rheingau-Taunus-Kreis","ags":"06439"}},{"attributes":{"cases7_Per_100k":878.032434034793,"last_Update":"10.03.2022, 00:00 Uhr","additionalProperties":{},"sn_V2":"00","gen":"Wetteraukreis","ags":"06440"}},{"attributes":{"cases7_Per_100k":1015.58157597353,"last_Update":"10.03.2022, 00:00 Uhr","additionalProperties":{},"sn_V2":"00","gen":"Gießen","ags":"06531"}},{"attributes":{"cases7_Per_100k":1195.07603414728,"last_Update":"10.03.2022, 00:00 Uhr","additionalProperties":{},"sn_V2":"00","gen":"Lahn-Dill-Kreis","ags":"06532"}},{"attributes":{"cases7_Per_100k":1258.3361870324,"last_Update":"10.03.2022, 00:00 Uhr","additionalProperties":{},"sn_V2":"00","gen":"Limburg-Weilburg","ags":"06533"}},{"attributes":{"cases7_Per_100k":980.061243661118,"last_Update":"10.03.2022, 00:00 Uhr","additionalProperties":{},"sn_V2":"00","gen":"Marburg-Biedenkopf","ags":"06534"}},{"attributes":{"cases7_Per_100k":1049.22942771027,"last_Update":"10.03.2022, 00:00 Uhr","additionalProperties":{},"sn_V2":"00","gen":"Vogelsbergkreis","ags":"06535"}},{"attributes":{"cases7_Per_100k":700.827663045641,"last_Update":"10.03.2022, 00:00 Uhr","additionalProperties":{},"sn_V2":"00","gen":"Kassel","ags":"06611"}},{"attributes":{"cases7_Per_100k":1326.32060370455,"last_Update":"10.03.2022, 00:00 Uhr","additionalProperties":{},"sn_V2":"00","gen":"Fulda","ags":"06631"}},{"attributes":{"cases7_Per_100k":951.75555260008,"last_Update":"10.03.2022, 00:00 Uhr","additionalProperties":{},"sn_V2":"00","gen":"Hersfeld-Rotenburg","ags":"06632"}},{"attributes":{"cases7_Per_100k":656.942621947875,"last_Update":"10.03.2022, 00:00 Uhr","additionalProperties":{},"sn_V2":"00","gen":"Kassel","ags":"06633"}},{"attributes":{"cases7_Per_100k":835.186832740214,"last_Update":"10.03.2022, 00:00 Uhr","additionalProperties":{},"sn_V2":"00","gen":"Schwalm-Eder-Kreis","ags":"06634"}},{"attributes":{"cases7_Per_100k":1112.26106511295,"last_Update":"10.03.2022, 00:00 Uhr","additionalProperties":{},"sn_V2":"00","gen":"Waldeck-Frankenberg","ags":"06635"}},{"attributes":{"cases7_Per_100k":1063.51078503888,"last_Update":"10.03.2022, 00:00 Uhr","additionalProperties":{},"sn_V2":"00","gen":"Werra-Meißner-Kreis","ags":"06636"}},{"attributes":{"cases7_Per_100k":1138.56845521572,"last_Update":"10.03.2022, 00:00 Uhr","additionalProperties":{},"sn_V2":"00","gen":"Koblenz","ags":"07111"}},{"attributes":{"cases7_Per_100k":1679.19741874171,"last_Update":"10.03.2022, 00:00 Uhr","additionalProperties":{},"sn_V2":"00","gen":"Ahrweiler","ags":"07131"}},{"attributes":{"cases7_Per_100k":1275.88370633759,"last_Update":"10.03.2022, 00:00 Uhr","additionalProperties":{},"sn_V2":"00","gen":"Altenkirchen (Westerwald)","ags":"07132"}},{"attributes":{"cases7_Per_100k":1869.02347145755,"last_Update":"10.03.2022, 00:00 Uhr","additionalProperties":{},"sn_V2":"00","gen":"Bad Kreuznach","ags":"07133"}},{"attributes":{"cases7_Per_100k":1135.7169367809,"last_Update":"10.03.2022, 00:00 Uhr","additionalProperties":{},"sn_V2":"00","gen":"Birkenfeld","ags":"07134"}},{"attributes":{"cases7_Per_100k":1947.12397284745,"last_Update":"10.03.2022, 00:00 Uhr","additionalProperties":{},"sn_V2":"00","gen":"Cochem-Zell","ags":"07135"}},{"attributes":{"cases7_Per_100k":1126.70285772816,"last_Update":"10.03.2022, 00:00 Uhr","additionalProperties":{},"sn_V2":"00","gen":"Mayen-Koblenz","ags":"07137"}},{"attributes":{"cases7_Per_100k":1200.23371247905,"last_Update":"10.03.2022, 00:00 Uhr","additionalProperties":{},"sn_V2":"00","gen":"Neuwied","ags":"07138"}},{"attributes":{"cases7_Per_100k":1381.99823986228,"last_Update":"10.03.2022, 00:00 Uhr","additionalProperties":{},"sn_V2":"00","gen":"Rhein-Hunsrück-Kreis","ags":"07140"}},{"attributes":{"cases7_Per_100k":1359.17894496386,"last_Update":"10.03.2022, 00:00 Uhr","additionalProperties":{},"sn_V2":"00","gen":"Rhein-Lahn-Kreis","ags":"07141"}},{"attributes":{"cases7_Per_100k":1449.98274416999,"last_Update":"10.03.2022, 00:00 Uhr","additionalProperties":{},"sn_V2":"00","gen":"Westerwaldkreis","ags":"07143"}},{"attributes":{"cases7_Per_100k":1622.7840323834,"last_Update":"10.03.2022, 00:00 Uhr","additionalProperties":{},"sn_V2":"00","gen":"Trier","ags":"07211"}},{"attributes":{"cases7_Per_100k":1466.92106314061,"last_Update":"10.03.2022, 00:00 Uhr","additionalProperties":{},"sn_V2":"00","gen":"Bernkastel-Wittlich","ags":"07231"}},{"attributes":{"cases7_Per_100k":1851.98141022438,"last_Update":"10.03.2022, 00:00 Uhr","additionalProperties":{},"sn_V2":"00","gen":"Eifelkreis Bitburg-Prüm","ags":"07232"}},{"attributes":{"cases7_Per_100k":2244.96206047181,"last_Update":"10.03.2022, 00:00 Uhr","additionalProperties":{},"sn_V2":"00","gen":"Vulkaneifel","ags":"07233"}},{"attributes":{"cases7_Per_100k":1543.84752844891,"last_Update":"10.03.2022, 00:00 Uhr","additionalProperties":{},"sn_V2":"00","gen":"Trier-Saarburg","ags":"07235"}},{"attributes":{"cases7_Per_100k":931.282051282051,"last_Update":"10.03.2022, 00:00 Uhr","additionalProperties":{},"sn_V2":"00","gen":"Frankenthal (Pfalz)","ags":"07311"}},{"attributes":{"cases7_Per_100k":1056.57121069214,"last_Update":"10.03.2022, 00:00 Uhr","additionalProperties":{},"sn_V2":"00","gen":"Kaiserslautern","ags":"07312"}},{"attributes":{"cases7_Per_100k":1154.54642818893,"last_Update":"10.03.2022, 00:00 Uhr","additionalProperties":{},"sn_V2":"00","gen":"Landau in der Pfalz","ags":"07313"}},{"attributes":{"cases7_Per_100k":774.236918815232,"last_Update":"10.03.2022, 00:00 Uhr","additionalProperties":{},"sn_V2":"00","gen":"Ludwigshafen am Rhein","ags":"07314"}},{"attributes":{"cases7_Per_100k":1509.74332521198,"last_Update":"10.03.2022, 00:00 Uhr","additionalProperties":{},"sn_V2":"00","gen":"Mainz","ags":"07315"}},{"attributes":{"cases7_Per_100k":1360.07203691892,"last_Update":"10.03.2022, 00:00 Uhr","additionalProperties":{},"sn_V2":"00","gen":"Neustadt an der Weinstraße","ags":"07316"}},{"attributes":{"cases7_Per_100k":1259.4583831143,"last_Update":"10.03.2022, 00:00 Uhr","additionalProperties":{},"sn_V2":"00","gen":"Pirmasens","ags":"07317"}},{"attributes":{"cases7_Per_100k":880.944403933703,"last_Update":"10.03.2022, 00:00 Uhr","additionalProperties":{},"sn_V2":"00","gen":"Speyer","ags":"07318"}},{"attributes":{"cases7_Per_100k":1111.92321978456,"last_Update":"10.03.2022, 00:00 Uhr","additionalProperties":{},"sn_V2":"00","gen":"Worms","ags":"07319"}},{"attributes":{"cases7_Per_100k":1382.3122849328,"last_Update":"10.03.2022, 00:00 Uhr","additionalProperties":{},"sn_V2":"00","gen":"Zweibrücken","ags":"07320"}},{"attributes":{"cases7_Per_100k":1090.92300042076,"last_Update":"10.03.2022, 00:00 Uhr","additionalProperties":{},"sn_V2":"00","gen":"Alzey-Worms","ags":"07331"}},{"attributes":{"cases7_Per_100k":1422.51360861327,"last_Update":"10.03.2022, 00:00 Uhr","additionalProperties":{},"sn_V2":"00","gen":"Bad Dürkheim","ags":"07332"}},{"attributes":{"cases7_Per_100k":1405.89629198163,"last_Update":"10.03.2022, 00:00 Uhr","additionalProperties":{},"sn_V2":"00","gen":"Donnersbergkreis","ags":"07333"}},{"attributes":{"cases7_Per_100k":1593.72432289971,"last_Update":"10.03.2022, 00:00 Uhr","additionalProperties":{},"sn_V2":"00","gen":"Germersheim","ags":"07334"}},{"attributes":{"cases7_Per_100k":1362.86681715576,"last_Update":"10.03.2022, 00:00 Uhr","additionalProperties":{},"sn_V2":"00","gen":"Kaiserslautern","ags":"07335"}},{"attributes":{"cases7_Per_100k":1041.29520005706,"last_Update":"10.03.2022, 00:00 Uhr","additionalProperties":{},"sn_V2":"00","gen":"Kusel","ags":"07336"}},{"attributes":{"cases7_Per_100k":1077.78269229033,"last_Update":"10.03.2022, 00:00 Uhr","additionalProperties":{},"sn_V2":"00","gen":"Südliche Weinstraße","ags":"07337"}},{"attributes":{"cases7_Per_100k":830.350104036083,"last_Update":"10.03.2022, 00:00 Uhr","additionalProperties":{},"sn_V2":"00","gen":"Rhein-Pfalz-Kreis","ags":"07338"}},{"attributes":{"cases7_Per_100k":1331.75747547571,"last_Update":"10.03.2022, 00:00 Uhr","additionalProperties":{},"sn_V2":"00","gen":"Mainz-Bingen","ags":"07339"}},{"attributes":{"cases7_Per_100k":1180.04045853001,"last_Update":"10.03.2022, 00:00 Uhr","additionalProperties":{},"sn_V2":"00","gen":"Südwestpfalz","ags":"07340"}},{"attributes":{"cases7_Per_100k":1041.24193842663,"last_Update":"10.03.2022, 00:00 Uhr","additionalProperties":{},"sn_V2":"00","gen":"Stuttgart","ags":"08111"}},{"attributes":{"cases7_Per_100k":1459.15733854588,"last_Update":"10.03.2022, 00:00 Uhr","additionalProperties":{},"sn_V2":"00","gen":"Böblingen","ags":"08115"}},{"attributes":{"cases7_Per_100k":1252.20898134805,"last_Update":"10.03.2022, 00:00 Uhr","additionalProperties":{},"sn_V2":"00","gen":"Esslingen","ags":"08116"}},{"attributes":{"cases7_Per_100k":1339.35644425209,"last_Update":"10.03.2022, 00:00 Uhr","additionalProperties":{},"sn_V2":"00","gen":"Göppingen","ags":"08117"}},{"attributes":{"cases7_Per_100k":975.281253497893,"last_Update":"10.03.2022, 00:00 Uhr","additionalProperties":{},"sn_V2":"00","gen":"Ludwigsburg","ags":"08118"}},{"attributes":{"cases7_Per_100k":1470.44368408981,"last_Update":"10.03.2022, 00:00 Uhr","additionalProperties":{},"sn_V2":"00","gen":"Rems-Murr-Kreis","ags":"08119"}},{"attributes":{"cases7_Per_100k":1384.64944882886,"last_Update":"10.03.2022, 00:00 Uhr","additionalProperties":{},"sn_V2":"00","gen":"Heilbronn","ags":"08121"}},{"attributes":{"cases7_Per_100k":1674.83247344549,"last_Update":"10.03.2022, 00:00 Uhr","additionalProperties":{},"sn_V2":"00","gen":"Heilbronn","ags":"08125"}},{"attributes":{"cases7_Per_100k":1656.54236686915,"last_Update":"10.03.2022, 00:00 Uhr","additionalProperties":{},"sn_V2":"00","gen":"Hohenlohekreis","ags":"08126"}},{"attributes":{"cases7_Per_100k":1644.59718993228,"last_Update":"10.03.2022, 00:00 Uhr","additionalProperties":{},"sn_V2":"00","gen":"Schwäbisch Hall","ags":"08127"}},{"attributes":{"cases7_Per_100k":1843.47773657713,"last_Update":"10.03.2022, 00:00 Uhr","additionalProperties":{},"sn_V2":"00","gen":"Main-Tauber-Kreis","ags":"08128"}},{"attributes":{"cases7_Per_100k":1483.29970183417,"last_Update":"10.03.2022, 00:00 Uhr","additionalProperties":{},"sn_V2":"00","gen":"Heidenheim","ags":"08135"}},{"attributes":{"cases7_Per_100k":2124.12581850115,"last_Update":"10.03.2022, 00:00 Uhr","additionalProperties":{},"sn_V2":"00","gen":"Ostalbkreis","ags":"08136"}},{"attributes":{"cases7_Per_100k":1298.49050478818,"last_Update":"10.03.2022, 00:00 Uhr","additionalProperties":{},"sn_V2":"00","gen":"Baden-Baden","ags":"08211"}},{"attributes":{"cases7_Per_100k":1625.94509071574,"last_Update":"10.03.2022, 00:00 Uhr","additionalProperties":{},"sn_V2":"00","gen":"Karlsruhe","ags":"08212"}},{"attributes":{"cases7_Per_100k":1801.93889699498,"last_Update":"10.03.2022, 00:00 Uhr","additionalProperties":{},"sn_V2":"00","gen":"Karlsruhe","ags":"08215"}},{"attributes":{"cases7_Per_100k":1624.36285767221,"last_Update":"10.03.2022, 00:00 Uhr","additionalProperties":{},"sn_V2":"00","gen":"Rastatt","ags":"08216"}},{"attributes":{"cases7_Per_100k":1664.34632514599,"last_Update":"10.03.2022, 00:00 Uhr","additionalProperties":{},"sn_V2":"00","gen":"Heidelberg","ags":"08221"}},{"attributes":{"cases7_Per_100k":1978.55489295204,"last_Update":"10.03.2022, 00:00 Uhr","additionalProperties":{},"sn_V2":"00","gen":"Mannheim","ags":"08222"}},{"attributes":{"cases7_Per_100k":2023.68616869615,"last_Update":"10.03.2022, 00:00 Uhr","additionalProperties":{},"sn_V2":"00","gen":"Neckar-Odenwald-Kreis","ags":"08225"}},{"attributes":{"cases7_Per_100k":1841.37036624939,"last_Update":"10.03.2022, 00:00 Uhr","additionalProperties":{},"sn_V2":"00","gen":"Rhein-Neckar-Kreis","ags":"08226"}},{"attributes":{"cases7_Per_100k":976.860081259523,"last_Update":"10.03.2022, 00:00 Uhr","additionalProperties":{},"sn_V2":"00","gen":"Pforzheim","ags":"08231"}},{"attributes":{"cases7_Per_100k":1283.18003858906,"last_Update":"10.03.2022, 00:00 Uhr","additionalProperties":{},"sn_V2":"00","gen":"Calw","ags":"08235"}},{"attributes":{"cases7_Per_100k":1260.06247747207,"last_Update":"10.03.2022, 00:00 Uhr","additionalProperties":{},"sn_V2":"00","gen":"Enzkreis","ags":"08236"}},{"attributes":{"cases7_Per_100k":2203.37264708864,"last_Update":"10.03.2022, 00:00 Uhr","additionalProperties":{},"sn_V2":"00","gen":"Freudenstadt","ags":"08237"}},{"attributes":{"cases7_Per_100k":1463.58361479172,"last_Update":"10.03.2022, 00:00 Uhr","additionalProperties":{},"sn_V2":"00","gen":"Freiburg im Breisgau","ags":"08311"}},{"attributes":{"cases7_Per_100k":1623.83384868632,"last_Update":"10.03.2022, 00:00 Uhr","additionalProperties":{},"sn_V2":"00","gen":"Breisgau-Hochschwarzwald","ags":"08315"}},{"attributes":{"cases7_Per_100k":1977.08285888938,"last_Update":"10.03.2022, 00:00 Uhr","additionalProperties":{},"sn_V2":"00","gen":"Emmendingen","ags":"08316"}},{"attributes":{"cases7_Per_100k":1587.9143742198,"last_Update":"10.03.2022, 00:00 Uhr","additionalProperties":{},"sn_V2":"00","gen":"Ortenaukreis","ags":"08317"}},{"attributes":{"cases7_Per_100k":2232.35306707761,"last_Update":"10.03.2022, 00:00 Uhr","additionalProperties":{},"sn_V2":"00","gen":"Rottweil","ags":"08325"}},{"attributes":{"cases7_Per_100k":3037.97587282498,"last_Update":"10.03.2022, 00:00 Uhr","additionalProperties":{},"sn_V2":"00","gen":"Schwarzwald-Baar-Kreis","ags":"08326"}},{"attributes":{"cases7_Per_100k":2101.89014836041,"last_Update":"10.03.2022, 00:00 Uhr","additionalProperties":{},"sn_V2":"00","gen":"Tuttlingen","ags":"08327"}},{"attributes":{"cases7_Per_100k":1669.36237259304,"last_Update":"10.03.2022, 00:00 Uhr","additionalProperties":{},"sn_V2":"00","gen":"Konstanz","ags":"08335"}},{"attributes":{"cases7_Per_100k":1248.02265318429,"last_Update":"10.03.2022, 00:00 Uhr","additionalProperties":{},"sn_V2":"00","gen":"Lörrach","ags":"08336"}},{"attributes":{"cases7_Per_100k":1497.92392999177,"last_Update":"10.03.2022, 00:00 Uhr","additionalProperties":{},"sn_V2":"00","gen":"Waldshut","ags":"08337"}},{"attributes":{"cases7_Per_100k":1507.84182095813,"last_Update":"10.03.2022, 00:00 Uhr","additionalProperties":{},"sn_V2":"00","gen":"Reutlingen","ags":"08415"}},{"attributes":{"cases7_Per_100k":1879.88847599914,"last_Update":"10.03.2022, 00:00 Uhr","additionalProperties":{},"sn_V2":"00","gen":"Tübingen","ags":"08416"}},{"attributes":{"cases7_Per_100k":2362.24204948858,"last_Update":"10.03.2022, 00:00 Uhr","additionalProperties":{},"sn_V2":"00","gen":"Zollernalbkreis","ags":"08417"}},{"attributes":{"cases7_Per_100k":1412.91879276927,"last_Update":"10.03.2022, 00:00 Uhr","additionalProperties":{},"sn_V2":"00","gen":"Ulm","ags":"08421"}},{"attributes":{"cases7_Per_100k":1887.95382535166,"last_Update":"10.03.2022, 00:00 Uhr","additionalProperties":{},"sn_V2":"00","gen":"Alb-Donau-Kreis","ags":"08425"}},{"attributes":{"cases7_Per_100k":2409.39431396786,"last_Update":"10.03.2022, 00:00 Uhr","additionalProperties":{},"sn_V2":"00","gen":"Biberach","ags":"08426"}},{"attributes":{"cases7_Per_100k":1695.26528102212,"last_Update":"10.03.2022, 00:00 Uhr","additionalProperties":{},"sn_V2":"00","gen":"Bodenseekreis","ags":"08435"}},{"attributes":{"cases7_Per_100k":2076.68737407656,"last_Update":"10.03.2022, 00:00 Uhr","additionalProperties":{},"sn_V2":"00","gen":"Ravensburg","ags":"08436"}},{"attributes":{"cases7_Per_100k":2685.07629099018,"last_Update":"10.03.2022, 00:00 Uhr","additionalProperties":{},"sn_V2":"00","gen":"Sigmaringen","ags":"08437"}},{"attributes":{"cases7_Per_100k":1500.5257316432,"last_Update":"10.03.2022, 00:00 Uhr","additionalProperties":{},"sn_V2":"00","gen":"Ingolstadt","ags":"09161"}},{"attributes":{"cases7_Per_100k":1234.17385543092,"last_Update":"10.03.2022, 00:00 Uhr","additionalProperties":{},"sn_V2":"00","gen":"München","ags":"09162"}},{"attributes":{"cases7_Per_100k":144.674560865531,"last_Update":"10.03.2022, 00:00 Uhr","additionalProperties":{},"sn_V2":"00","gen":"Rosenheim","ags":"09163"}},{"attributes":{"cases7_Per_100k":2086.80387626059,"last_Update":"10.03.2022, 00:00 Uhr","additionalProperties":{},"sn_V2":"00","gen":"Altötting","ags":"09171"}},{"attributes":{"cases7_Per_100k":2045.57638229236,"last_Update":"10.03.2022, 00:00 Uhr","additionalProperties":{},"sn_V2":"00","gen":"Berchtesgadener Land","ags":"09172"}},{"attributes":{"cases7_Per_100k":1677.69007581194,"last_Update":"10.03.2022, 00:00 Uhr","additionalProperties":{},"sn_V2":"00","gen":"Bad Tölz-Wolfratshausen","ags":"09173"}},{"attributes":{"cases7_Per_100k":1712.25591005499,"last_Update":"10.03.2022, 00:00 Uhr","additionalProperties":{},"sn_V2":"00","gen":"Dachau","ags":"09174"}},{"attributes":{"cases7_Per_100k":1852.30167047213,"last_Update":"10.03.2022, 00:00 Uhr","additionalProperties":{},"sn_V2":"00","gen":"Ebersberg","ags":"09175"}},{"attributes":{"cases7_Per_100k":2298.58300355188,"last_Update":"10.03.2022, 00:00 Uhr","additionalProperties":{},"sn_V2":"00","gen":"Eichstätt","ags":"09176"}},{"attributes":{"cases7_Per_100k":1961.97017805329,"last_Update":"10.03.2022, 00:00 Uhr","additionalProperties":{},"sn_V2":"00","gen":"Erding","ags":"09177"}},{"attributes":{"cases7_Per_100k":1517.91606817035,"last_Update":"10.03.2022, 00:00 Uhr","additionalProperties":{},"sn_V2":"00","gen":"Freising","ags":"09178"}},{"attributes":{"cases7_Per_100k":1627.50297156441,"last_Update":"10.03.2022, 00:00 Uhr","additionalProperties":{},"sn_V2":"00","gen":"Fürstenfeldbruck","ags":"09179"}},{"attributes":{"cases7_Per_100k":2995.04978533966,"last_Update":"10.03.2022, 00:00 Uhr","additionalProperties":{},"sn_V2":"00","gen":"Garmisch-Partenkirchen","ags":"09180"}},{"attributes":{"cases7_Per_100k":1850.12270800453,"last_Update":"10.03.2022, 00:00 Uhr","additionalProperties":{},"sn_V2":"00","gen":"Landsberg am Lech","ags":"09181"}},{"attributes":{"cases7_Per_100k":1170.85733108412,"last_Update":"10.03.2022, 00:00 Uhr","additionalProperties":{},"sn_V2":"00","gen":"Miesbach","ags":"09182"}},{"attributes":{"cases7_Per_100k":2238.09482928839,"last_Update":"10.03.2022, 00:00 Uhr","additionalProperties":{},"sn_V2":"00","gen":"Mühldorf a. Inn","ags":"09183"}},{"attributes":{"cases7_Per_100k":1287.44441425855,"last_Update":"10.03.2022, 00:00 Uhr","additionalProperties":{},"sn_V2":"00","gen":"München","ags":"09184"}},{"attributes":{"cases7_Per_100k":2483.37255704492,"last_Update":"10.03.2022, 00:00 Uhr","additionalProperties":{},"sn_V2":"00","gen":"Neuburg-Schrobenhausen","ags":"09185"}},{"attributes":{"cases7_Per_100k":2055.32494888793,"last_Update":"10.03.2022, 00:00 Uhr","additionalProperties":{},"sn_V2":"00","gen":"Pfaffenhofen a.d. Ilm","ags":"09186"}},{"attributes":{"cases7_Per_100k":155.12702457961,"last_Update":"10.03.2022, 00:00 Uhr","additionalProperties":{},"sn_V2":"00","gen":"Rosenheim","ags":"09187"}},{"attributes":{"cases7_Per_100k":1503.55025254374,"last_Update":"10.03.2022, 00:00 Uhr","additionalProperties":{},"sn_V2":"00","gen":"Starnberg","ags":"09188"}},{"attributes":{"cases7_Per_100k":1757.33160548779,"last_Update":"10.03.2022, 00:00 Uhr","additionalProperties":{},"sn_V2":"00","gen":"Traunstein","ags":"09189"}},{"attributes":{"cases7_Per_100k":1891.51865074118,"last_Update":"10.03.2022, 00:00 Uhr","additionalProperties":{},"sn_V2":"00","gen":"Weilheim-Schongau","ags":"09190"}},{"attributes":{"cases7_Per_100k":1694.38171491138,"last_Update":"10.03.2022, 00:00 Uhr","additionalProperties":{},"sn_V2":"00","gen":"Landshut","ags":"09261"}},{"attributes":{"cases7_Per_100k":2199.75197939521,"last_Update":"10.03.2022, 00:00 Uhr","additionalProperties":{},"sn_V2":"00","gen":"Passau","ags":"09262"}},{"attributes":{"cases7_Per_100k":1993.19499285894,"last_Update":"10.03.2022, 00:00 Uhr","additionalProperties":{},"sn_V2":"00","gen":"Straubing","ags":"09263"}},{"attributes":{"cases7_Per_100k":2519.27116899204,"last_Update":"10.03.2022, 00:00 Uhr","additionalProperties":{},"sn_V2":"00","gen":"Deggendorf","ags":"09271"}},{"attributes":{"cases7_Per_100k":2659.68987301385,"last_Update":"10.03.2022, 00:00 Uhr","additionalProperties":{},"sn_V2":"00","gen":"Freyung-Grafenau","ags":"09272"}},{"attributes":{"cases7_Per_100k":2351.89237377421,"last_Update":"10.03.2022, 00:00 Uhr","additionalProperties":{},"sn_V2":"00","gen":"Kelheim","ags":"09273"}},{"attributes":{"cases7_Per_100k":2183.74475001706,"last_Update":"10.03.2022, 00:00 Uhr","additionalProperties":{},"sn_V2":"00","gen":"Landshut","ags":"09274"}},{"attributes":{"cases7_Per_100k":2200.52312177572,"last_Update":"10.03.2022, 00:00 Uhr","additionalProperties":{},"sn_V2":"00","gen":"Passau","ags":"09275"}},{"attributes":{"cases7_Per_100k":2808.06591388253,"last_Update":"10.03.2022, 00:00 Uhr","additionalProperties":{},"sn_V2":"00","gen":"Regen","ags":"09276"}},{"attributes":{"cases7_Per_100k":2376.84729064039,"last_Update":"10.03.2022, 00:00 Uhr","additionalProperties":{},"sn_V2":"00","gen":"Rottal-Inn","ags":"09277"}},{"attributes":{"cases7_Per_100k":2316.57575310826,"last_Update":"10.03.2022, 00:00 Uhr","additionalProperties":{},"sn_V2":"00","gen":"Straubing-Bogen","ags":"09278"}},{"attributes":{"cases7_Per_100k":2371.3545308708,"last_Update":"10.03.2022, 00:00 Uhr","additionalProperties":{},"sn_V2":"00","gen":"Dingolfing-Landau","ags":"09279"}},{"attributes":{"cases7_Per_100k":1288.88043374869,"last_Update":"10.03.2022, 00:00 Uhr","additionalProperties":{},"sn_V2":"00","gen":"Amberg","ags":"09361"}},{"attributes":{"cases7_Per_100k":983.778813948907,"last_Update":"10.03.2022, 00:00 Uhr","additionalProperties":{},"sn_V2":"00","gen":"Regensburg","ags":"09362"}},{"attributes":{"cases7_Per_100k":1591.63042200541,"last_Update":"10.03.2022, 00:00 Uhr","additionalProperties":{},"sn_V2":"00","gen":"Weiden i.d. OPf.","ags":"09363"}},{"attributes":{"cases7_Per_100k":1312.6468475116,"last_Update":"10.03.2022, 00:00 Uhr","additionalProperties":{},"sn_V2":"00","gen":"Amberg-Sulzbach","ags":"09371"}},{"attributes":{"cases7_Per_100k":2117.19518478617,"last_Update":"10.03.2022, 00:00 Uhr","additionalProperties":{},"sn_V2":"00","gen":"Cham","ags":"09372"}},{"attributes":{"cases7_Per_100k":1774.81974486966,"last_Update":"10.03.2022, 00:00 Uhr","additionalProperties":{},"sn_V2":"00","gen":"Neumarkt i.d. OPf.","ags":"09373"}},{"attributes":{"cases7_Per_100k":1836.33578107665,"last_Update":"10.03.2022, 00:00 Uhr","additionalProperties":{},"sn_V2":"00","gen":"Neustadt a.d. Waldnaab","ags":"09374"}},{"attributes":{"cases7_Per_100k":1961.13756273324,"last_Update":"10.03.2022, 00:00 Uhr","additionalProperties":{},"sn_V2":"00","gen":"Regensburg","ags":"09375"}},{"attributes":{"cases7_Per_100k":1326.13132000242,"last_Update":"10.03.2022, 00:00 Uhr","additionalProperties":{},"sn_V2":"00","gen":"Schwandorf","ags":"09376"}},{"attributes":{"cases7_Per_100k":2097.74603883062,"last_Update":"10.03.2022, 00:00 Uhr","additionalProperties":{},"sn_V2":"00","gen":"Tirschenreuth","ags":"09377"}},{"attributes":{"cases7_Per_100k":1520.72410465086,"last_Update":"10.03.2022, 00:00 Uhr","additionalProperties":{},"sn_V2":"00","gen":"Bamberg","ags":"09461"}},{"attributes":{"cases7_Per_100k":1559.79904926534,"last_Update":"10.03.2022, 00:00 Uhr","additionalProperties":{},"sn_V2":"00","gen":"Bayreuth","ags":"09462"}},{"attributes":{"cases7_Per_100k":2076.29401106704,"last_Update":"10.03.2022, 00:00 Uhr","additionalProperties":{},"sn_V2":"00","gen":"Coburg","ags":"09463"}},{"attributes":{"cases7_Per_100k":2089.74387355279,"last_Update":"10.03.2022, 00:00 Uhr","additionalProperties":{},"sn_V2":"00","gen":"Hof","ags":"09464"}},{"attributes":{"cases7_Per_100k":2158.0099934236,"last_Update":"10.03.2022, 00:00 Uhr","additionalProperties":{},"sn_V2":"00","gen":"Bamberg","ags":"09471"}},{"attributes":{"cases7_Per_100k":1679.22144310805,"last_Update":"10.03.2022, 00:00 Uhr","additionalProperties":{},"sn_V2":"00","gen":"Bayreuth","ags":"09472"}},{"attributes":{"cases7_Per_100k":2168.16254865948,"last_Update":"10.03.2022, 00:00 Uhr","additionalProperties":{},"sn_V2":"00","gen":"Coburg","ags":"09473"}},{"attributes":{"cases7_Per_100k":1852.487135506,"last_Update":"10.03.2022, 00:00 Uhr","additionalProperties":{},"sn_V2":"00","gen":"Forchheim","ags":"09474"}},{"attributes":{"cases7_Per_100k":2010.11404752333,"last_Update":"10.03.2022, 00:00 Uhr","additionalProperties":{},"sn_V2":"00","gen":"Hof","ags":"09475"}},{"attributes":{"cases7_Per_100k":2317.83588275187,"last_Update":"10.03.2022, 00:00 Uhr","additionalProperties":{},"sn_V2":"00","gen":"Kronach","ags":"09476"}},{"attributes":{"cases7_Per_100k":1876.01500812007,"last_Update":"10.03.2022, 00:00 Uhr","additionalProperties":{},"sn_V2":"00","gen":"Kulmbach","ags":"09477"}},{"attributes":{"cases7_Per_100k":2071.28083690537,"last_Update":"10.03.2022, 00:00 Uhr","additionalProperties":{},"sn_V2":"00","gen":"Lichtenfels","ags":"09478"}},{"attributes":{"cases7_Per_100k":2224.4143718565,"last_Update":"10.03.2022, 00:00 Uhr","additionalProperties":{},"sn_V2":"00","gen":"Wunsiedel i. Fichtelgebirge","ags":"09479"}},{"attributes":{"cases7_Per_100k":1681.82145342002,"last_Update":"10.03.2022, 00:00 Uhr","additionalProperties":{},"sn_V2":"00","gen":"Ansbach","ags":"09561"}},{"attributes":{"cases7_Per_100k":1455.71028162121,"last_Update":"10.03.2022, 00:00 Uhr","additionalProperties":{},"sn_V2":"00","gen":"Erlangen","ags":"09562"}},{"attributes":{"cases7_Per_100k":1400.68474454661,"last_Update":"10.03.2022, 00:00 Uhr","additionalProperties":{},"sn_V2":"00","gen":"Fürth","ags":"09563"}},{"attributes":{"cases7_Per_100k":1537.02019036239,"last_Update":"10.03.2022, 00:00 Uhr","additionalProperties":{},"sn_V2":"00","gen":"Nürnberg","ags":"09564"}},{"attributes":{"cases7_Per_100k":1361.55494933749,"last_Update":"10.03.2022, 00:00 Uhr","additionalProperties":{},"sn_V2":"00","gen":"Schwabach","ags":"09565"}},{"attributes":{"cases7_Per_100k":1692.78421722895,"last_Update":"10.03.2022, 00:00 Uhr","additionalProperties":{},"sn_V2":"00","gen":"Ansbach","ags":"09571"}},{"attributes":{"cases7_Per_100k":1635.7119582926,"last_Update":"10.03.2022, 00:00 Uhr","additionalProperties":{},"sn_V2":"00","gen":"Erlangen-Höchstadt","ags":"09572"}},{"attributes":{"cases7_Per_100k":1627.70125110578,"last_Update":"10.03.2022, 00:00 Uhr","additionalProperties":{},"sn_V2":"00","gen":"Fürth","ags":"09573"}},{"attributes":{"cases7_Per_100k":1495.82512869355,"last_Update":"10.03.2022, 00:00 Uhr","additionalProperties":{},"sn_V2":"00","gen":"Nürnberger Land","ags":"09574"}},{"attributes":{"cases7_Per_100k":1011.13832056245,"last_Update":"10.03.2022, 00:00 Uhr","additionalProperties":{},"sn_V2":"00","gen":"Neustadt a.d. Aisch-Bad Windsheim","ags":"09575"}},{"attributes":{"cases7_Per_100k":1871.54001006543,"last_Update":"10.03.2022, 00:00 Uhr","additionalProperties":{},"sn_V2":"00","gen":"Roth","ags":"09576"}},{"attributes":{"cases7_Per_100k":1980.71848355184,"last_Update":"10.03.2022, 00:00 Uhr","additionalProperties":{},"sn_V2":"00","gen":"Weißenburg-Gunzenhausen","ags":"09577"}},{"attributes":{"cases7_Per_100k":1216.51754212651,"last_Update":"10.03.2022, 00:00 Uhr","additionalProperties":{},"sn_V2":"00","gen":"Aschaffenburg","ags":"09661"}},{"attributes":{"cases7_Per_100k":964.009077439562,"last_Update":"10.03.2022, 00:00 Uhr","additionalProperties":{},"sn_V2":"00","gen":"Schweinfurt","ags":"09662"}},{"attributes":{"cases7_Per_100k":2053.49969280212,"last_Update":"10.03.2022, 00:00 Uhr","additionalProperties":{},"sn_V2":"00","gen":"Würzburg","ags":"09663"}},{"attributes":{"cases7_Per_100k":1315.14159099497,"last_Update":"10.03.2022, 00:00 Uhr","additionalProperties":{},"sn_V2":"00","gen":"Aschaffenburg","ags":"09671"}},{"attributes":{"cases7_Per_100k":1463.6179472516,"last_Update":"10.03.2022, 00:00 Uhr","additionalProperties":{},"sn_V2":"00","gen":"Bad Kissingen","ags":"09672"}},{"attributes":{"cases7_Per_100k":2297.82417305999,"last_Update":"10.03.2022, 00:00 Uhr","additionalProperties":{},"sn_V2":"00","gen":"Rhön-Grabfeld","ags":"09673"}},{"attributes":{"cases7_Per_100k":2526.25333728864,"last_Update":"10.03.2022, 00:00 Uhr","additionalProperties":{},"sn_V2":"00","gen":"Haßberge","ags":"09674"}},{"attributes":{"cases7_Per_100k":1882.30675274821,"last_Update":"10.03.2022, 00:00 Uhr","additionalProperties":{},"sn_V2":"00","gen":"Kitzingen","ags":"09675"}},{"attributes":{"cases7_Per_100k":1877.38362474076,"last_Update":"10.03.2022, 00:00 Uhr","additionalProperties":{},"sn_V2":"00","gen":"Miltenberg","ags":"09676"}},{"attributes":{"cases7_Per_100k":1823.36318028831,"last_Update":"10.03.2022, 00:00 Uhr","additionalProperties":{},"sn_V2":"00","gen":"Main-Spessart","ags":"09677"}},{"attributes":{"cases7_Per_100k":1171.61830318542,"last_Update":"10.03.2022, 00:00 Uhr","additionalProperties":{},"sn_V2":"00","gen":"Schweinfurt","ags":"09678"}},{"attributes":{"cases7_Per_100k":2232.3706030228,"last_Update":"10.03.2022, 00:00 Uhr","additionalProperties":{},"sn_V2":"00","gen":"Würzburg","ags":"09679"}},{"attributes":{"cases7_Per_100k":1222.32363181557,"last_Update":"10.03.2022, 00:00 Uhr","additionalProperties":{},"sn_V2":"00","gen":"Augsburg","ags":"09761"}},{"attributes":{"cases7_Per_100k":1370.2924186109,"last_Update":"10.03.2022, 00:00 Uhr","additionalProperties":{},"sn_V2":"00","gen":"Kaufbeuren","ags":"09762"}},{"attributes":{"cases7_Per_100k":1840.73107049608,"last_Update":"10.03.2022, 00:00 Uhr","additionalProperties":{},"sn_V2":"00","gen":"Kempten (Allgäu)","ags":"09763"}},{"attributes":{"cases7_Per_100k":1789.90081154193,"last_Update":"10.03.2022, 00:00 Uhr","additionalProperties":{},"sn_V2":"00","gen":"Memmingen","ags":"09764"}},{"attributes":{"cases7_Per_100k":1938.17395425998,"last_Update":"10.03.2022, 00:00 Uhr","additionalProperties":{},"sn_V2":"00","gen":"Aichach-Friedberg","ags":"09771"}},{"attributes":{"cases7_Per_100k":1681.51621727237,"last_Update":"10.03.2022, 00:00 Uhr","additionalProperties":{},"sn_V2":"00","gen":"Augsburg","ags":"09772"}},{"attributes":{"cases7_Per_100k":2421.47943852139,"last_Update":"10.03.2022, 00:00 Uhr","additionalProperties":{},"sn_V2":"00","gen":"Dillingen a.d. Donau","ags":"09773"}},{"attributes":{"cases7_Per_100k":1489.68918345872,"last_Update":"10.03.2022, 00:00 Uhr","additionalProperties":{},"sn_V2":"00","gen":"Günzburg","ags":"09774"}},{"attributes":{"cases7_Per_100k":1565.210467345,"last_Update":"10.03.2022, 00:00 Uhr","additionalProperties":{},"sn_V2":"00","gen":"Neu-Ulm","ags":"09775"}},{"attributes":{"cases7_Per_100k":1958.94499604069,"last_Update":"10.03.2022, 00:00 Uhr","additionalProperties":{},"sn_V2":"00","gen":"Lindau (Bodensee)","ags":"09776"}},{"attributes":{"cases7_Per_100k":1913.9295454065,"last_Update":"10.03.2022, 00:00 Uhr","additionalProperties":{},"sn_V2":"00","gen":"Ostallgäu","ags":"09777"}},{"attributes":{"cases7_Per_100k":1919.76136394735,"last_Update":"10.03.2022, 00:00 Uhr","additionalProperties":{},"sn_V2":"00","gen":"Unterallgäu","ags":"09778"}},{"attributes":{"cases7_Per_100k":2005.59840385933,"last_Update":"10.03.2022, 00:00 Uhr","additionalProperties":{},"sn_V2":"00","gen":"Donau-Ries","ags":"09779"}},{"attributes":{"cases7_Per_100k":2244.92668321519,"last_Update":"10.03.2022, 00:00 Uhr","additionalProperties":{},"sn_V2":"00","gen":"Oberallgäu","ags":"09780"}},{"attributes":{"cases7_Per_100k":1620.14277775403,"last_Update":"10.03.2022, 00:00 Uhr","additionalProperties":{},"sn_V2":"00","gen":"Regionalverband Saarbrücken","ags":"10041"}},{"attributes":{"cases7_Per_100k":1697.09387171285,"last_Update":"10.03.2022, 00:00 Uhr","additionalProperties":{},"sn_V2":"00","gen":"Merzig-Wadern","ags":"10042"}},{"attributes":{"cases7_Per_100k":1664.98947946208,"last_Update":"10.03.2022, 00:00 Uhr","additionalProperties":{},"sn_V2":"00","gen":"Neunkirchen","ags":"10043"}},{"attributes":{"cases7_Per_100k":1762.22823281647,"last_Update":"10.03.2022, 00:00 Uhr","additionalProperties":{},"sn_V2":"00","gen":"Saarlouis","ags":"10044"}},{"attributes":{"cases7_Per_100k":1648.35940588468,"last_Update":"10.03.2022, 00:00 Uhr","additionalProperties":{},"sn_V2":"00","gen":"Saarpfalz-Kreis","ags":"10045"}},{"attributes":{"cases7_Per_100k":1783.52494852992,"last_Update":"10.03.2022, 00:00 Uhr","additionalProperties":{},"sn_V2":"00","gen":"St. Wendel","ags":"10046"}},{"attributes":{"cases7_Per_100k":2548.58411993337,"last_Update":"10.03.2022, 00:00 Uhr","additionalProperties":{},"sn_V2":"00","gen":"Brandenburg an der Havel","ags":"12051"}},{"attributes":{"cases7_Per_100k":1851.19512022129,"last_Update":"10.03.2022, 00:00 Uhr","additionalProperties":{},"sn_V2":"00","gen":"Cottbus","ags":"12052"}},{"attributes":{"cases7_Per_100k":1845.12847496273,"last_Update":"10.03.2022, 00:00 Uhr","additionalProperties":{},"sn_V2":"00","gen":"Frankfurt (Oder)","ags":"12053"}},{"attributes":{"cases7_Per_100k":1279.43243718151,"last_Update":"10.03.2022, 00:00 Uhr","additionalProperties":{},"sn_V2":"00","gen":"Potsdam","ags":"12054"}},{"attributes":{"cases7_Per_100k":727.008748658877,"last_Update":"10.03.2022, 00:00 Uhr","additionalProperties":{},"sn_V2":"00","gen":"Barnim","ags":"12060"}},{"attributes":{"cases7_Per_100k":1606.31447760161,"last_Update":"10.03.2022, 00:00 Uhr","additionalProperties":{},"sn_V2":"00","gen":"Dahme-Spreewald","ags":"12061"}},{"attributes":{"cases7_Per_100k":2264.43092446951,"last_Update":"10.03.2022, 00:00 Uhr","additionalProperties":{},"sn_V2":"00","gen":"Elbe-Elster","ags":"12062"}},{"attributes":{"cases7_Per_100k":988.505886710425,"last_Update":"10.03.2022, 00:00 Uhr","additionalProperties":{},"sn_V2":"00","gen":"Havelland","ags":"12063"}},{"attributes":{"cases7_Per_100k":1298.71447044803,"last_Update":"10.03.2022, 00:00 Uhr","additionalProperties":{},"sn_V2":"00","gen":"Märkisch-Oderland","ags":"12064"}},{"attributes":{"cases7_Per_100k":1045.1188886918,"last_Update":"10.03.2022, 00:00 Uhr","additionalProperties":{},"sn_V2":"00","gen":"Oberhavel","ags":"12065"}},{"attributes":{"cases7_Per_100k":1301.708550131,"last_Update":"10.03.2022, 00:00 Uhr","additionalProperties":{},"sn_V2":"00","gen":"Oberspreewald-Lausitz","ags":"12066"}},{"attributes":{"cases7_Per_100k":1634.90930185859,"last_Update":"10.03.2022, 00:00 Uhr","additionalProperties":{},"sn_V2":"00","gen":"Oder-Spree","ags":"12067"}},{"attributes":{"cases7_Per_100k":1791.35292688851,"last_Update":"10.03.2022, 00:00 Uhr","additionalProperties":{},"sn_V2":"00","gen":"Ostprignitz-Ruppin","ags":"12068"}},{"attributes":{"cases7_Per_100k":1404.42478688164,"last_Update":"10.03.2022, 00:00 Uhr","additionalProperties":{},"sn_V2":"00","gen":"Potsdam-Mittelmark","ags":"12069"}},{"attributes":{"cases7_Per_100k":1808.24222035324,"last_Update":"10.03.2022, 00:00 Uhr","additionalProperties":{},"sn_V2":"00","gen":"Prignitz","ags":"12070"}},{"attributes":{"cases7_Per_100k":1590.99556680323,"last_Update":"10.03.2022, 00:00 Uhr","additionalProperties":{},"sn_V2":"00","gen":"Spree-Neiße","ags":"12071"}},{"attributes":{"cases7_Per_100k":1453.76965853317,"last_Update":"10.03.2022, 00:00 Uhr","additionalProperties":{},"sn_V2":"00","gen":"Teltow-Fläming","ags":"12072"}},{"attributes":{"cases7_Per_100k":1441.86046511628,"last_Update":"10.03.2022, 00:00 Uhr","additionalProperties":{},"sn_V2":"00","gen":"Uckermark","ags":"12073"}},{"attributes":{"cases7_Per_100k":1671.28254432917,"last_Update":"10.03.2022, 00:00 Uhr","additionalProperties":{},"sn_V2":"00","gen":"Rostock","ags":"13003"}},{"attributes":{"cases7_Per_100k":2016.54655942432,"last_Update":"10.03.2022, 00:00 Uhr","additionalProperties":{},"sn_V2":"00","gen":"Schwerin","ags":"13004"}},{"attributes":{"cases7_Per_100k":1203.99756642912,"last_Update":"10.03.2022, 00:00 Uhr","additionalProperties":{},"sn_V2":"00","gen":"Mecklenburgische Seenplatte","ags":"13071"}},{"attributes":{"cases7_Per_100k":2333.78786761996,"last_Update":"10.03.2022, 00:00 Uhr","additionalProperties":{},"sn_V2":"00","gen":"Rostock","ags":"13072"}},{"attributes":{"cases7_Per_100k":2291.21096089767,"last_Update":"10.03.2022, 00:00 Uhr","additionalProperties":{},"sn_V2":"00","gen":"Vorpommern-Rügen","ags":"13073"}},{"attributes":{"cases7_Per_100k":2197.81611014401,"last_Update":"10.03.2022, 00:00 Uhr","additionalProperties":{},"sn_V2":"00","gen":"Nordwestmecklenburg","ags":"13074"}},{"attributes":{"cases7_Per_100k":1910.73617420146,"last_Update":"10.03.2022, 00:00 Uhr","additionalProperties":{},"sn_V2":"00","gen":"Vorpommern-Greifswald","ags":"13075"}},{"attributes":{"cases7_Per_100k":2115.70778497385,"last_Update":"10.03.2022, 00:00 Uhr","additionalProperties":{},"sn_V2":"00","gen":"Ludwigslust-Parchim","ags":"13076"}},{"attributes":{"cases7_Per_100k":1186.5745230175,"last_Update":"10.03.2022, 00:00 Uhr","additionalProperties":{},"sn_V2":"00","gen":"Chemnitz","ags":"14511"}},{"attributes":{"cases7_Per_100k":1399.44624710394,"last_Update":"10.03.2022, 00:00 Uhr","additionalProperties":{},"sn_V2":"00","gen":"Erzgebirgskreis","ags":"14521"}},{"attributes":{"cases7_Per_100k":1106.89479026384,"last_Update":"10.03.2022, 00:00 Uhr","additionalProperties":{},"sn_V2":"00","gen":"Mittelsachsen","ags":"14522"}},{"attributes":{"cases7_Per_100k":1516.71467810009,"last_Update":"10.03.2022, 00:00 Uhr","additionalProperties":{},"sn_V2":"00","gen":"Vogtlandkreis","ags":"14523"}},{"attributes":{"cases7_Per_100k":1255.95690199434,"last_Update":"10.03.2022, 00:00 Uhr","additionalProperties":{},"sn_V2":"00","gen":"Zwickau","ags":"14524"}},{"attributes":{"cases7_Per_100k":1403.2040875398,"last_Update":"10.03.2022, 00:00 Uhr","additionalProperties":{},"sn_V2":"00","gen":"Dresden","ags":"14612"}},{"attributes":{"cases7_Per_100k":1296.60078520855,"last_Update":"10.03.2022, 00:00 Uhr","additionalProperties":{},"sn_V2":"00","gen":"Bautzen","ags":"14625"}},{"attributes":{"cases7_Per_100k":1168.59170331819,"last_Update":"10.03.2022, 00:00 Uhr","additionalProperties":{},"sn_V2":"00","gen":"Görlitz","ags":"14626"}},{"attributes":{"cases7_Per_100k":1548.43970362481,"last_Update":"10.03.2022, 00:00 Uhr","additionalProperties":{},"sn_V2":"00","gen":"Meißen","ags":"14627"}},{"attributes":{"cases7_Per_100k":1398.32136056423,"last_Update":"10.03.2022, 00:00 Uhr","additionalProperties":{},"sn_V2":"00","gen":"Sächsische Schweiz-Osterzgebirge","ags":"14628"}},{"attributes":{"cases7_Per_100k":1551.14787955675,"last_Update":"10.03.2022, 00:00 Uhr","additionalProperties":{},"sn_V2":"00","gen":"Leipzig","ags":"14713"}},{"attributes":{"cases7_Per_100k":1580.19397335769,"last_Update":"10.03.2022, 00:00 Uhr","additionalProperties":{},"sn_V2":"00","gen":"Leipzig","ags":"14729"}},{"attributes":{"cases7_Per_100k":1538.15765482871,"last_Update":"10.03.2022, 00:00 Uhr","additionalProperties":{},"sn_V2":"00","gen":"Nordsachsen","ags":"14730"}},{"attributes":{"cases7_Per_100k":1427.77931799279,"last_Update":"10.03.2022, 00:00 Uhr","additionalProperties":{},"sn_V2":"00","gen":"Dessau-Roßlau","ags":"15001"}},{"attributes":{"cases7_Per_100k":1624.45084396612,"last_Update":"10.03.2022, 00:00 Uhr","additionalProperties":{},"sn_V2":"00","gen":"Halle (Saale)","ags":"15002"}},{"attributes":{"cases7_Per_100k":1671.50885378009,"last_Update":"10.03.2022, 00:00 Uhr","additionalProperties":{},"sn_V2":"00","gen":"Magdeburg","ags":"15003"}},{"attributes":{"cases7_Per_100k":2111.57739426996,"last_Update":"10.03.2022, 00:00 Uhr","additionalProperties":{},"sn_V2":"00","gen":"Altmarkkreis Salzwedel","ags":"15081"}},{"attributes":{"cases7_Per_100k":1311.56299891233,"last_Update":"10.03.2022, 00:00 Uhr","additionalProperties":{},"sn_V2":"00","gen":"Anhalt-Bitterfeld","ags":"15082"}},{"attributes":{"cases7_Per_100k":1716.04120374985,"last_Update":"10.03.2022, 00:00 Uhr","additionalProperties":{},"sn_V2":"00","gen":"Börde","ags":"15083"}},{"attributes":{"cases7_Per_100k":1647.61529365392,"last_Update":"10.03.2022, 00:00 Uhr","additionalProperties":{},"sn_V2":"00","gen":"Burgenlandkreis","ags":"15084"}},{"attributes":{"cases7_Per_100k":2213.53240905321,"last_Update":"10.03.2022, 00:00 Uhr","additionalProperties":{},"sn_V2":"00","gen":"Harz","ags":"15085"}},{"attributes":{"cases7_Per_100k":2169.94955426552,"last_Update":"10.03.2022, 00:00 Uhr","additionalProperties":{},"sn_V2":"00","gen":"Jerichower Land","ags":"15086"}},{"attributes":{"cases7_Per_100k":1872.9897524123,"last_Update":"10.03.2022, 00:00 Uhr","additionalProperties":{},"sn_V2":"00","gen":"Mansfeld-Südharz","ags":"15087"}},{"attributes":{"cases7_Per_100k":1518.25724783846,"last_Update":"10.03.2022, 00:00 Uhr","additionalProperties":{},"sn_V2":"00","gen":"Saalekreis","ags":"15088"}},{"attributes":{"cases7_Per_100k":1780.67503480798,"last_Update":"10.03.2022, 00:00 Uhr","additionalProperties":{},"sn_V2":"00","gen":"Salzlandkreis","ags":"15089"}},{"attributes":{"cases7_Per_100k":1434.58388016473,"last_Update":"10.03.2022, 00:00 Uhr","additionalProperties":{},"sn_V2":"00","gen":"Stendal","ags":"15090"}},{"attributes":{"cases7_Per_100k":1593.59020815718,"last_Update":"10.03.2022, 00:00 Uhr","additionalProperties":{},"sn_V2":"00","gen":"Wittenberg","ags":"15091"}},{"attributes":{"cases7_Per_100k":840.461973307377,"last_Update":"10.03.2022, 00:00 Uhr","additionalProperties":{},"sn_V2":"00","gen":"Erfurt","ags":"16051"}},{"attributes":{"cases7_Per_100k":1836.61507066409,"last_Update":"10.03.2022, 00:00 Uhr","additionalProperties":{},"sn_V2":"00","gen":"Gera","ags":"16052"}},{"attributes":{"cases7_Per_100k":1947.0608953229,"last_Update":"10.03.2022, 00:00 Uhr","additionalProperties":{},"sn_V2":"00","gen":"Jena","ags":"16053"}},{"attributes":{"cases7_Per_100k":1376.56271465861,"last_Update":"10.03.2022, 00:00 Uhr","additionalProperties":{},"sn_V2":"00","gen":"Suhl","ags":"16054"}},{"attributes":{"cases7_Per_100k":1872.56136901287,"last_Update":"10.03.2022, 00:00 Uhr","additionalProperties":{},"sn_V2":"00","gen":"Weimar","ags":"16055"}},{"attributes":{"cases7_Per_100k":2833.21436111921,"last_Update":"10.03.2022, 00:00 Uhr","additionalProperties":{},"sn_V2":"00","gen":"Eichsfeld","ags":"16061"}},{"attributes":{"cases7_Per_100k":2697.19608033375,"last_Update":"10.03.2022, 00:00 Uhr","additionalProperties":{},"sn_V2":"00","gen":"Nordhausen","ags":"16062"}},{"attributes":{"cases7_Per_100k":1631.89255769459,"last_Update":"10.03.2022, 00:00 Uhr","additionalProperties":{},"sn_V2":"00","gen":"Wartburgkreis","ags":"16063"}},{"attributes":{"cases7_Per_100k":1900.72567798777,"last_Update":"10.03.2022, 00:00 Uhr","additionalProperties":{},"sn_V2":"00","gen":"Unstrut-Hainich-Kreis","ags":"16064"}},{"attributes":{"cases7_Per_100k":1600.88136884198,"last_Update":"10.03.2022, 00:00 Uhr","additionalProperties":{},"sn_V2":"00","gen":"Kyffhäuserkreis","ags":"16065"}},{"attributes":{"cases7_Per_100k":1477.77303788604,"last_Update":"10.03.2022, 00:00 Uhr","additionalProperties":{},"sn_V2":"00","gen":"Schmalkalden-Meiningen","ags":"16066"}},{"attributes":{"cases7_Per_100k":1394.88566693668,"last_Update":"10.03.2022, 00:00 Uhr","additionalProperties":{},"sn_V2":"00","gen":"Gotha","ags":"16067"}},{"attributes":{"cases7_Per_100k":1876.79974532247,"last_Update":"10.03.2022, 00:00 Uhr","additionalProperties":{},"sn_V2":"00","gen":"Sömmerda","ags":"16068"}},{"attributes":{"cases7_Per_100k":1594.42032686415,"last_Update":"10.03.2022, 00:00 Uhr","additionalProperties":{},"sn_V2":"00","gen":"Hildburghausen","ags":"16069"}},{"attributes":{"cases7_Per_100k":1493.28636630494,"last_Update":"10.03.2022, 00:00 Uhr","additionalProperties":{},"sn_V2":"00","gen":"Ilm-Kreis","ags":"16070"}},{"attributes":{"cases7_Per_100k":1821.58437739242,"last_Update":"10.03.2022, 00:00 Uhr","additionalProperties":{},"sn_V2":"00","gen":"Weimarer Land","ags":"16071"}},{"attributes":{"cases7_Per_100k":1167.51980927004,"last_Update":"10.03.2022, 00:00 Uhr","additionalProperties":{},"sn_V2":"00","gen":"Sonneberg","ags":"16072"}},{"attributes":{"cases7_Per_100k":2131.40915810807,"last_Update":"10.03.2022, 00:00 Uhr","additionalProperties":{},"sn_V2":"00","gen":"Saalfeld-Rudolstadt","ags":"16073"}},{"attributes":{"cases7_Per_100k":2437.93469860896,"last_Update":"10.03.2022, 00:00 Uhr","additionalProperties":{},"sn_V2":"00","gen":"Saale-Holzland-Kreis","ags":"16074"}},{"attributes":{"cases7_Per_100k":1823.38758288125,"last_Update":"10.03.2022, 00:00 Uhr","additionalProperties":{},"sn_V2":"00","gen":"Saale-Orla-Kreis","ags":"16075"}},{"attributes":{"cases7_Per_100k":869.988000165515,"last_Update":"10.03.2022, 00:00 Uhr","additionalProperties":{},"sn_V2":"00","gen":"Greiz","ags":"16076"}},{"attributes":{"cases7_Per_100k":2194.53121463172,"last_Update":"10.03.2022, 00:00 Uhr","additionalProperties":{},"sn_V2":"00","gen":"Altenburger Land","ags":"16077"}},{"attributes":{"cases7_Per_100k":678.037886955183,"last_Update":"10.03.2022, 00:00 Uhr","additionalProperties":{},"sn_V2":null,"gen":"Berlin Reinickendorf","ags":null}},{"attributes":{"cases7_Per_100k":577.440603624657,"last_Update":"10.03.2022, 00:00 Uhr","additionalProperties":{},"sn_V2":null,"gen":"Berlin Charlottenburg-Wilmersdorf","ags":null}},{"attributes":{"cases7_Per_100k":800.756066111827,"last_Update":"10.03.2022, 00:00 Uhr","additionalProperties":{},"sn_V2":null,"gen":"Berlin Treptow-Köpenick","ags":null}},{"attributes":{"cases7_Per_100k":823.381256695539,"last_Update":"10.03.2022, 00:00 Uhr","additionalProperties":{},"sn_V2":null,"gen":"Berlin Pankow","ags":null}},{"attributes":{"cases7_Per_100k":380.209036479346,"last_Update":"10.03.2022, 00:00 Uhr","additionalProperties":{},"sn_V2":null,"gen":"Berlin Neukölln","ags":null}},{"attributes":{"cases7_Per_100k":369.514220646907,"last_Update":"10.03.2022, 00:00 Uhr","additionalProperties":{},"sn_V2":null,"gen":"Berlin Lichtenberg","ags":null}},{"attributes":{"cases7_Per_100k":899.750434186138,"last_Update":"10.03.2022, 00:00 Uhr","additionalProperties":{},"sn_V2":null,"gen":"Berlin Marzahn-Hellersdorf","ags":null}},{"attributes":{"cases7_Per_100k":814.207056739663,"last_Update":"10.03.2022, 00:00 Uhr","additionalProperties":{},"sn_V2":null,"gen":"Berlin Spandau","ags":null}},{"attributes":{"cases7_Per_100k":800.575509994348,"last_Update":"10.03.2022, 00:00 Uhr","additionalProperties":{},"sn_V2":null,"gen":"Berlin Steglitz-Zehlendorf","ags":null}},{"attributes":{"cases7_Per_100k":680.226706640219,"last_Update":"10.03.2022, 00:00 Uhr","additionalProperties":{},"sn_V2":null,"gen":"Berlin Mitte","ags":null}},{"attributes":{"cases7_Per_100k":849.1816195695,"last_Update":"10.03.2022, 00:00 Uhr","additionalProperties":{},"sn_V2":null,"gen":"Berlin Friedrichshain-Kreuzberg","ags":null}},{"attributes":{"cases7_Per_100k":674.780835403872,"last_Update":"10.03.2022, 00:00 Uhr","additionalProperties":{},"sn_V2":null,"gen":"Berlin Tempelhof-Schöneberg","ags":null}}],"additionalProperties":{}}