{"objectIdFieldName":"OBJECTID","uniqueIdField":{"name":"OBJECTID","isSystemMaintained":true,"additionalProperties":{}},"globalIdFieldName":"","geometryType":"esriGeometryPolygon","spatialReference":{"wkid":4326,"latestWkid":4326,"additionalProperties":{}},"fields":[{"name":"OBJECTID","type":"esriFieldTypeOID","alias":"OBJECTID","sqlType":"sqlTypeOther","length":null,"domain":null,"defaultValue":null,"additionalProperties":{}},{"name":"ADE","type":"esriFieldTypeSmallInteger","alias":"ADE","sqlType":"sqlTypeOther","length":null,"domain":null,"defaultValue":null,"additionalProperties":{}},{"name":"GF","type":"esriFieldTypeSmallInteger","alias":"GF","sqlType":"sqlTypeOther","length":null,"domain":null,"defaultValue":null,"additionalProperties":{}},{"name":"BSG","type":"esriFieldTypeSmallInteger","alias":"BSG","sqlType":"sqlTypeOther","length":null,"domain":null,"defaultValue":null,"additionalProperties":{}},{"name":"RS","type":"esriFieldTypeString","alias":"RS","sqlType":"sqlTypeOther","length":5,"domain":null,"defaultValue":null,"additionalProperties":{}},{"name":"AGS","type":"esriFieldTypeString","alias":"AGS","sqlType":"sqlTypeOther","length":5,"domain":null,"defaultValue":null,"additionalProperties":{}},{"name":"SDV_RS","type":"esriFieldTypeString","alias":"SDV_RS","sqlType":"sqlTypeOther","length":12,"domain":null,"defaultValue":null,"additionalProperties":{}},{"name":"GEN","type":"esriFieldTypeString","alias":"GEN","sqlType":"sqlTypeOther","length":33,"domain":null,"defaultValue":null,"additionalProperties":{}},{"name":"BEZ","type":"esriFieldTypeString","alias":"BEZ","sqlType":"sqlTypeOther","length":16,"domain":null,"defaultValue":null,"additionalProperties":{}},{"name":"IBZ","type":"esriFieldTypeSmallInteger","alias":"IBZ","sqlType":"sqlTypeOther","length":null,"domain":null,"defaultValue":null,"additionalProperties":{}},{"name":"BEM","type":"esriFieldTypeString","alias":"BEM","sqlType":"sqlTypeOther","length":13,"domain":null,"defaultValue":null,"additionalProperties":{}},{"name":"NBD","type":"esriFieldTypeString","alias":"NBD","sqlType":"sqlTypeOther","length":4,"domain":null,"defaultValue":null,"additionalProperties":{}},{"name":"SN_L","type":"esriFieldTypeString","alias":"SN_L","sqlType":"sqlTypeOther","length":2,"domain":null,"defaultValue":null,"additionalProperties":{}},{"name":"SN_R","type":"esriFieldTypeString","alias":"SN_R","sqlType":"sqlTypeOther","length":1,"domain":null,"defaultValue":null,"additionalProperties":{}},{"name":"SN_K","type":"esriFieldTypeString","alias":"SN_K","sqlType":"sqlTypeOther","length":2,"domain":null,"defaultValue":null,"additionalProperties":{}},{"name":"SN_V1","type":"esriFieldTypeString","alias":"SN_V1","sqlType":"sqlTypeOther","length":2,"domain":null,"defaultValue":null,"additionalProperties":{}},{"name":"SN_V2","type":"esriFieldTypeString","alias":"SN_V2","sqlType":"sqlTypeOther","length":2,"domain":null,"defaultValue":null,"additionalProperties":{}},{"name":"SN_G","type":"esriFieldTypeString","alias":"SN_G","sqlType":"sqlTypeOther","length":3,"domain":null,"defaultValue":null,"additionalProperties":{}},{"name":"FK_S3","type":"esriFieldTypeString","alias":"FK_S3","sqlType":"sqlTypeOther","length":1,"domain":null,"defaultValue":null,"additionalProperties":{}},{"name":"NUTS","type":"esriFieldTypeString","alias":"NUTS","sqlType":"sqlTypeOther","length":5,"domain":null,"defaultValue":null,"additionalProperties":{}},{"name":"RS_0","type":"esriFieldTypeString","alias":"RS_0","sqlType":"sqlTypeOther","length":12,"domain":null,"defaultValue":null,"additionalProperties":{}},{"name":"AGS_0","type":"esriFieldTypeString","alias":"AGS_0","sqlType":"sqlTypeOther","length":8,"domain":null,"defaultValue":null,"additionalProperties":{}},{"name":"WSK","type":"esriFieldTypeString","alias":"WSK","sqlType":"sqlTypeOther","length":23,"domain":null,"defaultValue":null,"additionalProperties":{}},{"name":"EWZ","type":"esriFieldTypeInteger","alias":"Einwohnerzahl","sqlType":"sqlTypeOther","length":null,"domain":null,"defaultValue":null,"additionalProperties":{}},{"name":"KFL","type":"esriFieldTypeDouble","alias":"KFL","sqlType":"sqlTypeOther","length":null,"domain":null,"defaultValue":null,"additionalProperties":{}},{"name":"DEBKG_ID","type":"esriFieldTypeString","alias":"DEBKG_ID","sqlType":"sqlTypeOther","length":16,"domain":null,"defaultValue":null,"additionalProperties":{}},{"name":"Shape__Area","type":"esriFieldTypeDouble","alias":"Shape__Area","sqlType":"sqlTypeDouble","length":null,"domain":null,"defaultValue":null,"additionalProperties":{}},{"name":"Shape__Length","type":"esriFieldTypeDouble","alias":"Shape__Length","sqlType":"sqlTypeDouble","length":null,"domain":null,"defaultValue":null,"additionalProperties":{}},{"name":"death_rate","type":"esriFieldTypeDouble","alias":"Sterberate","sqlType":"sqlTypeOther","length":null,"domain":null,"defaultValue":null,"additionalProperties":{}},{"name":"cases","type":"esriFieldTypeInteger","alias":"Fälle","sqlType":"sqlTypeOther","length":null,"domain":null,"defaultValue":null,"additionalProperties":{}},{"name":"deaths","type":"esriFieldTypeInteger","alias":"Todesfälle","sqlType":"sqlTypeOther","length":null,"domain":null,"defaultValue":null,"additionalProperties":{}},{"name":"cases_per_100k","type":"esriFieldTypeDouble","alias":"Fälle/100.000 EW","sqlType":"sqlTypeOther","length":null,"domain":null,"defaultValue":null,"additionalProperties":{}},{"name":"cases_per_population","type":"esriFieldTypeDouble","alias":"Betroffenenrate %","sqlType":"sqlTypeOther","length":null,"domain":null,"defaultValue":null,"additionalProperties":{}},{"name":"BL","type":"esriFieldTypeString","alias":"Bundesland","sqlType":"sqlTypeOther","length":256,"domain":null,"defaultValue":null,"additionalProperties":{}},{"name":"BL_ID","type":"esriFieldTypeString","alias":"Bundesland ID","sqlType":"sqlTypeOther","length":256,"domain":null,"defaultValue":null,"additionalProperties":{}},{"name":"county","type":"esriFieldTypeString","alias":"Landkreis","sqlType":"sqlTypeOther","length":256,"domain":null,"defaultValue":null,"additionalProperties":{}},{"name":"last_update","type":"esriFieldTypeString","alias":"Aktualisierung","sqlType":"sqlTypeOther","length":256,"domain":null,"defaultValue":null,"additionalProperties":{}},{"name":"cases7_per_100k","type":"esriFieldTypeDouble","alias":"Fälle letzte 7 Tage/100.000 EW","sqlType":"sqlTypeOther","length":null,"domain":null,"defaultValue":null,"additionalProperties":{}},{"name":"recovered","type":"esriFieldTypeInteger","alias":"Genesene","sqlType":"sqlTypeOther","length":null,"domain":null,"defaultValue":null,"additionalProperties":{}},{"name":"EWZ_BL","type":"esriFieldTypeInteger","alias":"EWZ_BL","sqlType":"sqlTypeOther","length":null,"domain":null,"defaultValue":null,"additionalProperties":{}},{"name":"cases7_bl_per_100k","type":"esriFieldTypeDouble","alias":"Bundeslandweite Fälle der letzten 7 Tage/100.000 EW","sqlType":"sqlTypeOther","length":null,"domain":null,"defaultValue":null,"additionalProperties":{}},{"name":"cases7_bl","type":"esriFieldTypeInteger","alias":"Fälle der letzten 7 Tage pro Bundesland","sqlType":"sqlTypeOther","length":null,"domain":null,"defaultValue":null,"additionalProperties":{}},{"name":"death7_bl","type":"esriFieldTypeInteger","alias":"Todesfälle der letzten 7 Tage pro Bundesland","sqlType":"sqlTypeOther","length":null,"domain":null,"defaultValue":null,"additionalProperties":{}},{"name":"cases7_lk","type":"esriFieldTypeInteger","alias":"Fälle der letzten 7 Tage pro Landkreis","sqlType":"sqlTypeOther","length":null,"domain":null,"defaultValue":null,"additionalProperties":{}},{"name":"death7_lk","type":"esriFieldTypeInteger","alias":"Todesfälle der letzten 7 Tage pro Landkreis","sqlType":"sqlTypeOther","length":null,"domain":null,"defaultValue":null,"additionalProperties":{}},{"name":"cases7_per_100k_txt","type":"esriFieldTypeString","alias":"Fälle der letzten 7 Tage/100000 EW (Text)","sqlType":"sqlTypeOther","length":256,"domain":null,"defaultValue":null,"additionalProperties":{}},{"name":"AdmUnitId","type":"esriFieldTypeInteger","alias":"AdmUnitId","sqlType":"sqlTypeInteger","length":null,"domain":null,"defaultValue":null,"additionalProperties":{}}],"features":[{"attributes":{"cases7_Per_100k":845.064158160429,"last_Update":"17.01.2022, 00:00 Uhr","additionalProperties":{},"sn_V2":"00","gen":"Flensburg","ags":"01001"}},{"attributes":{"cases7_Per_100k":1032.84252699705,"last_Update":"17.01.2022, 00:00 Uhr","additionalProperties":{},"sn_V2":"00","gen":"Kiel","ags":"01002"}},{"attributes":{"cases7_Per_100k":1047.50609230655,"last_Update":"17.01.2022, 00:00 Uhr","additionalProperties":{},"sn_V2":"00","gen":"Lübeck","ags":"01003"}},{"attributes":{"cases7_Per_100k":564.420249045742,"last_Update":"17.01.2022, 00:00 Uhr","additionalProperties":{},"sn_V2":"00","gen":"Neumünster","ags":"01004"}},{"attributes":{"cases7_Per_100k":556.843851078041,"last_Update":"17.01.2022, 00:00 Uhr","additionalProperties":{},"sn_V2":"00","gen":"Dithmarschen","ags":"01051"}},{"attributes":{"cases7_Per_100k":583.473929460914,"last_Update":"17.01.2022, 00:00 Uhr","additionalProperties":{},"sn_V2":"00","gen":"Herzogtum Lauenburg","ags":"01053"}},{"attributes":{"cases7_Per_100k":771.775742310661,"last_Update":"17.01.2022, 00:00 Uhr","additionalProperties":{},"sn_V2":"00","gen":"Nordfriesland","ags":"01054"}},{"attributes":{"cases7_Per_100k":506.236134341173,"last_Update":"17.01.2022, 00:00 Uhr","additionalProperties":{},"sn_V2":"00","gen":"Ostholstein","ags":"01055"}},{"attributes":{"cases7_Per_100k":475.897629973036,"last_Update":"17.01.2022, 00:00 Uhr","additionalProperties":{},"sn_V2":"00","gen":"Pinneberg","ags":"01056"}},{"attributes":{"cases7_Per_100k":405.866118296445,"last_Update":"17.01.2022, 00:00 Uhr","additionalProperties":{},"sn_V2":"00","gen":"Plön","ags":"01057"}},{"attributes":{"cases7_Per_100k":642.731061088567,"last_Update":"17.01.2022, 00:00 Uhr","additionalProperties":{},"sn_V2":"00","gen":"Rendsburg-Eckernförde","ags":"01058"}},{"attributes":{"cases7_Per_100k":958.810147695253,"last_Update":"17.01.2022, 00:00 Uhr","additionalProperties":{},"sn_V2":"00","gen":"Schleswig-Flensburg","ags":"01059"}},{"attributes":{"cases7_Per_100k":876.956335631837,"last_Update":"17.01.2022, 00:00 Uhr","additionalProperties":{},"sn_V2":"00","gen":"Segeberg","ags":"01060"}},{"attributes":{"cases7_Per_100k":429.972610285679,"last_Update":"17.01.2022, 00:00 Uhr","additionalProperties":{},"sn_V2":"00","gen":"Steinburg","ags":"01061"}},{"attributes":{"cases7_Per_100k":348.587079419892,"last_Update":"17.01.2022, 00:00 Uhr","additionalProperties":{},"sn_V2":"00","gen":"Stormarn","ags":"01062"}},{"attributes":{"cases7_Per_100k":805.839529538272,"last_Update":"17.01.2022, 00:00 Uhr","additionalProperties":{},"sn_V2":"00","gen":"Hamburg","ags":"02000"}},{"attributes":{"cases7_Per_100k":532.263709914267,"last_Update":"17.01.2022, 00:00 Uhr","additionalProperties":{},"sn_V2":"00","gen":"Braunschweig","ags":"03101"}},{"attributes":{"cases7_Per_100k":601.73685325323,"last_Update":"17.01.2022, 00:00 Uhr","additionalProperties":{},"sn_V2":"00","gen":"Salzgitter","ags":"03102"}},{"attributes":{"cases7_Per_100k":477.228682170543,"last_Update":"17.01.2022, 00:00 Uhr","additionalProperties":{},"sn_V2":"00","gen":"Wolfsburg","ags":"03103"}},{"attributes":{"cases7_Per_100k":363.375783599564,"last_Update":"17.01.2022, 00:00 Uhr","additionalProperties":{},"sn_V2":"00","gen":"Gifhorn","ags":"03151"}},{"attributes":{"cases7_Per_100k":260.6022808268,"last_Update":"17.01.2022, 00:00 Uhr","additionalProperties":{},"sn_V2":"00","gen":"Goslar","ags":"03153"}},{"attributes":{"cases7_Per_100k":307.04342315173,"last_Update":"17.01.2022, 00:00 Uhr","additionalProperties":{},"sn_V2":"00","gen":"Helmstedt","ags":"03154"}},{"attributes":{"cases7_Per_100k":244.361472847039,"last_Update":"17.01.2022, 00:00 Uhr","additionalProperties":{},"sn_V2":"00","gen":"Northeim","ags":"03155"}},{"attributes":{"cases7_Per_100k":379.84747210035,"last_Update":"17.01.2022, 00:00 Uhr","additionalProperties":{},"sn_V2":"00","gen":"Peine","ags":"03157"}},{"attributes":{"cases7_Per_100k":348.522549241377,"last_Update":"17.01.2022, 00:00 Uhr","additionalProperties":{},"sn_V2":"00","gen":"Wolfenbüttel","ags":"03158"}},{"attributes":{"cases7_Per_100k":271.380055572708,"last_Update":"17.01.2022, 00:00 Uhr","additionalProperties":{},"sn_V2":"00","gen":"Göttingen","ags":"03159"}},{"attributes":{"cases7_Per_100k":451.472739390477,"last_Update":"17.01.2022, 00:00 Uhr","additionalProperties":{},"sn_V2":"00","gen":"Region Hannover","ags":"03241"}},{"attributes":{"cases7_Per_100k":588.796360834954,"last_Update":"17.01.2022, 00:00 Uhr","additionalProperties":{},"sn_V2":"00","gen":"Diepholz","ags":"03251"}},{"attributes":{"cases7_Per_100k":356.710189796743,"last_Update":"17.01.2022, 00:00 Uhr","additionalProperties":{},"sn_V2":"00","gen":"Hameln-Pyrmont","ags":"03252"}},{"attributes":{"cases7_Per_100k":341.968460488485,"last_Update":"17.01.2022, 00:00 Uhr","additionalProperties":{},"sn_V2":"00","gen":"Hildesheim","ags":"03254"}},{"attributes":{"cases7_Per_100k":297.691113421739,"last_Update":"17.01.2022, 00:00 Uhr","additionalProperties":{},"sn_V2":"00","gen":"Holzminden","ags":"03255"}},{"attributes":{"cases7_Per_100k":331.291873895351,"last_Update":"17.01.2022, 00:00 Uhr","additionalProperties":{},"sn_V2":"00","gen":"Nienburg (Weser)","ags":"03256"}},{"attributes":{"cases7_Per_100k":389.505448025959,"last_Update":"17.01.2022, 00:00 Uhr","additionalProperties":{},"sn_V2":"00","gen":"Schaumburg","ags":"03257"}},{"attributes":{"cases7_Per_100k":347.853232693744,"last_Update":"17.01.2022, 00:00 Uhr","additionalProperties":{},"sn_V2":"00","gen":"Celle","ags":"03351"}},{"attributes":{"cases7_Per_100k":459.698429782825,"last_Update":"17.01.2022, 00:00 Uhr","additionalProperties":{},"sn_V2":"00","gen":"Cuxhaven","ags":"03352"}},{"attributes":{"cases7_Per_100k":753.859133804137,"last_Update":"17.01.2022, 00:00 Uhr","additionalProperties":{},"sn_V2":"00","gen":"Harburg","ags":"03353"}},{"attributes":{"cases7_Per_100k":313.382677360163,"last_Update":"17.01.2022, 00:00 Uhr","additionalProperties":{},"sn_V2":"00","gen":"Lüchow-Dannenberg","ags":"03354"}},{"attributes":{"cases7_Per_100k":509.675143159552,"last_Update":"17.01.2022, 00:00 Uhr","additionalProperties":{},"sn_V2":"00","gen":"Lüneburg","ags":"03355"}},{"attributes":{"cases7_Per_100k":716.154919748779,"last_Update":"17.01.2022, 00:00 Uhr","additionalProperties":{},"sn_V2":"00","gen":"Osterholz","ags":"03356"}},{"attributes":{"cases7_Per_100k":204.880658536289,"last_Update":"17.01.2022, 00:00 Uhr","additionalProperties":{},"sn_V2":"00","gen":"Rotenburg (Wümme)","ags":"03357"}},{"attributes":{"cases7_Per_100k":266.884338290095,"last_Update":"17.01.2022, 00:00 Uhr","additionalProperties":{},"sn_V2":"00","gen":"Heidekreis","ags":"03358"}},{"attributes":{"cases7_Per_100k":422.191598046329,"last_Update":"17.01.2022, 00:00 Uhr","additionalProperties":{},"sn_V2":"00","gen":"Stade","ags":"03359"}},{"attributes":{"cases7_Per_100k":354.34176695547,"last_Update":"17.01.2022, 00:00 Uhr","additionalProperties":{},"sn_V2":"00","gen":"Uelzen","ags":"03360"}},{"attributes":{"cases7_Per_100k":846.81698576766,"last_Update":"17.01.2022, 00:00 Uhr","additionalProperties":{},"sn_V2":"00","gen":"Verden","ags":"03361"}},{"attributes":{"cases7_Per_100k":1248.98391030025,"last_Update":"17.01.2022, 00:00 Uhr","additionalProperties":{},"sn_V2":"00","gen":"Delmenhorst","ags":"03401"}},{"attributes":{"cases7_Per_100k":340.858964590769,"last_Update":"17.01.2022, 00:00 Uhr","additionalProperties":{},"sn_V2":"00","gen":"Emden","ags":"03402"}},{"attributes":{"cases7_Per_100k":545.384864832994,"last_Update":"17.01.2022, 00:00 Uhr","additionalProperties":{},"sn_V2":"00","gen":"Oldenburg (Oldb)","ags":"03403"}},{"attributes":{"cases7_Per_100k":551.079933992194,"last_Update":"17.01.2022, 00:00 Uhr","additionalProperties":{},"sn_V2":"00","gen":"Osnabrück","ags":"03404"}},{"attributes":{"cases7_Per_100k":316.535663461411,"last_Update":"17.01.2022, 00:00 Uhr","additionalProperties":{},"sn_V2":"00","gen":"Wilhelmshaven","ags":"03405"}},{"attributes":{"cases7_Per_100k":514.155185724632,"last_Update":"17.01.2022, 00:00 Uhr","additionalProperties":{},"sn_V2":"00","gen":"Ammerland","ags":"03451"}},{"attributes":{"cases7_Per_100k":239.249545162953,"last_Update":"17.01.2022, 00:00 Uhr","additionalProperties":{},"sn_V2":"00","gen":"Aurich","ags":"03452"}},{"attributes":{"cases7_Per_100k":335.395523425553,"last_Update":"17.01.2022, 00:00 Uhr","additionalProperties":{},"sn_V2":"00","gen":"Cloppenburg","ags":"03453"}},{"attributes":{"cases7_Per_100k":306.752196515976,"last_Update":"17.01.2022, 00:00 Uhr","additionalProperties":{},"sn_V2":"00","gen":"Emsland","ags":"03454"}},{"attributes":{"cases7_Per_100k":240.474482424144,"last_Update":"17.01.2022, 00:00 Uhr","additionalProperties":{},"sn_V2":"00","gen":"Friesland","ags":"03455"}},{"attributes":{"cases7_Per_100k":446.729663284768,"last_Update":"17.01.2022, 00:00 Uhr","additionalProperties":{},"sn_V2":"00","gen":"Grafschaft Bentheim","ags":"03456"}},{"attributes":{"cases7_Per_100k":258.334645416747,"last_Update":"17.01.2022, 00:00 Uhr","additionalProperties":{},"sn_V2":"00","gen":"Leer","ags":"03457"}},{"attributes":{"cases7_Per_100k":602.432549613211,"last_Update":"17.01.2022, 00:00 Uhr","additionalProperties":{},"sn_V2":"00","gen":"Oldenburg","ags":"03458"}},{"attributes":{"cases7_Per_100k":395.58128472116,"last_Update":"17.01.2022, 00:00 Uhr","additionalProperties":{},"sn_V2":"00","gen":"Osnabrück","ags":"03459"}},{"attributes":{"cases7_Per_100k":649.974251555345,"last_Update":"17.01.2022, 00:00 Uhr","additionalProperties":{},"sn_V2":"00","gen":"Vechta","ags":"03460"}},{"attributes":{"cases7_Per_100k":502.688536442095,"last_Update":"17.01.2022, 00:00 Uhr","additionalProperties":{},"sn_V2":"00","gen":"Wesermarsch","ags":"03461"}},{"attributes":{"cases7_Per_100k":193.433709744877,"last_Update":"17.01.2022, 00:00 Uhr","additionalProperties":{},"sn_V2":"00","gen":"Wittmund","ags":"03462"}},{"attributes":{"cases7_Per_100k":1477.30301302745,"last_Update":"17.01.2022, 00:00 Uhr","additionalProperties":{},"sn_V2":"00","gen":"Bremen","ags":"04011"}},{"attributes":{"cases7_Per_100k":950.183608231989,"last_Update":"17.01.2022, 00:00 Uhr","additionalProperties":{},"sn_V2":"00","gen":"Bremerhaven","ags":"04012"}},{"attributes":{"cases7_Per_100k":510.859387967892,"last_Update":"17.01.2022, 00:00 Uhr","additionalProperties":{},"sn_V2":"00","gen":"Düsseldorf","ags":"05111"}},{"attributes":{"cases7_Per_100k":668.905088881495,"last_Update":"17.01.2022, 00:00 Uhr","additionalProperties":{},"sn_V2":"00","gen":"Duisburg","ags":"05112"}},{"attributes":{"cases7_Per_100k":631.336761587528,"last_Update":"17.01.2022, 00:00 Uhr","additionalProperties":{},"sn_V2":"00","gen":"Essen","ags":"05113"}},{"attributes":{"cases7_Per_100k":668.741513991994,"last_Update":"17.01.2022, 00:00 Uhr","additionalProperties":{},"sn_V2":"00","gen":"Krefeld","ags":"05114"}},{"attributes":{"cases7_Per_100k":610.401863940077,"last_Update":"17.01.2022, 00:00 Uhr","additionalProperties":{},"sn_V2":"00","gen":"Mönchengladbach","ags":"05116"}},{"attributes":{"cases7_Per_100k":547.621415741775,"last_Update":"17.01.2022, 00:00 Uhr","additionalProperties":{},"sn_V2":"00","gen":"Mülheim an der Ruhr","ags":"05117"}},{"attributes":{"cases7_Per_100k":582.632678965099,"last_Update":"17.01.2022, 00:00 Uhr","additionalProperties":{},"sn_V2":"00","gen":"Oberhausen","ags":"05119"}},{"attributes":{"cases7_Per_100k":601.707378313426,"last_Update":"17.01.2022, 00:00 Uhr","additionalProperties":{},"sn_V2":"00","gen":"Remscheid","ags":"05120"}},{"attributes":{"cases7_Per_100k":714.8555526939,"last_Update":"17.01.2022, 00:00 Uhr","additionalProperties":{},"sn_V2":"00","gen":"Solingen","ags":"05122"}},{"attributes":{"cases7_Per_100k":842.244031053171,"last_Update":"17.01.2022, 00:00 Uhr","additionalProperties":{},"sn_V2":"00","gen":"Wuppertal","ags":"05124"}},{"attributes":{"cases7_Per_100k":415.834890588228,"last_Update":"17.01.2022, 00:00 Uhr","additionalProperties":{},"sn_V2":"00","gen":"Kleve","ags":"05154"}},{"attributes":{"cases7_Per_100k":554.383240901714,"last_Update":"17.01.2022, 00:00 Uhr","additionalProperties":{},"sn_V2":"00","gen":"Mettmann","ags":"05158"}},{"attributes":{"cases7_Per_100k":336.282441853005,"last_Update":"17.01.2022, 00:00 Uhr","additionalProperties":{},"sn_V2":"00","gen":"Rhein-Kreis Neuss","ags":"05162"}},{"attributes":{"cases7_Per_100k":514.5108127663,"last_Update":"17.01.2022, 00:00 Uhr","additionalProperties":{},"sn_V2":"00","gen":"Viersen","ags":"05166"}},{"attributes":{"cases7_Per_100k":497.703824929963,"last_Update":"17.01.2022, 00:00 Uhr","additionalProperties":{},"sn_V2":"00","gen":"Wesel","ags":"05170"}},{"attributes":{"cases7_Per_100k":531.491716049719,"last_Update":"17.01.2022, 00:00 Uhr","additionalProperties":{},"sn_V2":"00","gen":"Bonn","ags":"05314"}},{"attributes":{"cases7_Per_100k":421.412868320938,"last_Update":"17.01.2022, 00:00 Uhr","additionalProperties":{},"sn_V2":"00","gen":"Köln","ags":"05315"}},{"attributes":{"cases7_Per_100k":784.600835850035,"last_Update":"17.01.2022, 00:00 Uhr","additionalProperties":{},"sn_V2":"00","gen":"Leverkusen","ags":"05316"}},{"attributes":{"cases7_Per_100k":588.181398448883,"last_Update":"17.01.2022, 00:00 Uhr","additionalProperties":{},"sn_V2":"00","gen":"Städteregion Aachen","ags":"05334"}},{"attributes":{"cases7_Per_100k":572.904880440522,"last_Update":"17.01.2022, 00:00 Uhr","additionalProperties":{},"sn_V2":"00","gen":"Düren","ags":"05358"}},{"attributes":{"cases7_Per_100k":545.132034811791,"last_Update":"17.01.2022, 00:00 Uhr","additionalProperties":{},"sn_V2":"00","gen":"Rhein-Erft-Kreis","ags":"05362"}},{"attributes":{"cases7_Per_100k":354.498633971156,"last_Update":"17.01.2022, 00:00 Uhr","additionalProperties":{},"sn_V2":"00","gen":"Euskirchen","ags":"05366"}},{"attributes":{"cases7_Per_100k":425.02086111566,"last_Update":"17.01.2022, 00:00 Uhr","additionalProperties":{},"sn_V2":"00","gen":"Heinsberg","ags":"05370"}},{"attributes":{"cases7_Per_100k":489.144236820894,"last_Update":"17.01.2022, 00:00 Uhr","additionalProperties":{},"sn_V2":"00","gen":"Oberbergischer Kreis","ags":"05374"}},{"attributes":{"cases7_Per_100k":546.818462624658,"last_Update":"17.01.2022, 00:00 Uhr","additionalProperties":{},"sn_V2":"00","gen":"Rheinisch-Bergischer Kreis","ags":"05378"}},{"attributes":{"cases7_Per_100k":480.033312513013,"last_Update":"17.01.2022, 00:00 Uhr","additionalProperties":{},"sn_V2":"00","gen":"Rhein-Sieg-Kreis","ags":"05382"}},{"attributes":{"cases7_Per_100k":486.421099260572,"last_Update":"17.01.2022, 00:00 Uhr","additionalProperties":{},"sn_V2":"00","gen":"Bottrop","ags":"05512"}},{"attributes":{"cases7_Per_100k":448.080893846124,"last_Update":"17.01.2022, 00:00 Uhr","additionalProperties":{},"sn_V2":"00","gen":"Gelsenkirchen","ags":"05513"}},{"attributes":{"cases7_Per_100k":550.563679863971,"last_Update":"17.01.2022, 00:00 Uhr","additionalProperties":{},"sn_V2":"00","gen":"Münster","ags":"05515"}},{"attributes":{"cases7_Per_100k":566.284303760709,"last_Update":"17.01.2022, 00:00 Uhr","additionalProperties":{},"sn_V2":"00","gen":"Borken","ags":"05554"}},{"attributes":{"cases7_Per_100k":433.143644206024,"last_Update":"17.01.2022, 00:00 Uhr","additionalProperties":{},"sn_V2":"00","gen":"Coesfeld","ags":"05558"}},{"attributes":{"cases7_Per_100k":217.24285730583,"last_Update":"17.01.2022, 00:00 Uhr","additionalProperties":{},"sn_V2":"00","gen":"Recklinghausen","ags":"05562"}},{"attributes":{"cases7_Per_100k":493.309861511791,"last_Update":"17.01.2022, 00:00 Uhr","additionalProperties":{},"sn_V2":"00","gen":"Steinfurt","ags":"05566"}},{"attributes":{"cases7_Per_100k":524.841664353663,"last_Update":"17.01.2022, 00:00 Uhr","additionalProperties":{},"sn_V2":"00","gen":"Warendorf","ags":"05570"}},{"attributes":{"cases7_Per_100k":419.478934601465,"last_Update":"17.01.2022, 00:00 Uhr","additionalProperties":{},"sn_V2":"00","gen":"Bielefeld","ags":"05711"}},{"attributes":{"cases7_Per_100k":566.035667099759,"last_Update":"17.01.2022, 00:00 Uhr","additionalProperties":{},"sn_V2":"00","gen":"Gütersloh","ags":"05754"}},{"attributes":{"cases7_Per_100k":439.837635254064,"last_Update":"17.01.2022, 00:00 Uhr","additionalProperties":{},"sn_V2":"00","gen":"Herford","ags":"05758"}},{"attributes":{"cases7_Per_100k":294.140801122172,"last_Update":"17.01.2022, 00:00 Uhr","additionalProperties":{},"sn_V2":"00","gen":"Höxter","ags":"05762"}},{"attributes":{"cases7_Per_100k":430.87298613713,"last_Update":"17.01.2022, 00:00 Uhr","additionalProperties":{},"sn_V2":"00","gen":"Lippe","ags":"05766"}},{"attributes":{"cases7_Per_100k":502.465594482225,"last_Update":"17.01.2022, 00:00 Uhr","additionalProperties":{},"sn_V2":"00","gen":"Minden-Lübbecke","ags":"05770"}},{"attributes":{"cases7_Per_100k":275.349862973714,"last_Update":"17.01.2022, 00:00 Uhr","additionalProperties":{},"sn_V2":"00","gen":"Paderborn","ags":"05774"}},{"attributes":{"cases7_Per_100k":574.83248914815,"last_Update":"17.01.2022, 00:00 Uhr","additionalProperties":{},"sn_V2":"00","gen":"Bochum","ags":"05911"}},{"attributes":{"cases7_Per_100k":780.845879502328,"last_Update":"17.01.2022, 00:00 Uhr","additionalProperties":{},"sn_V2":"00","gen":"Dortmund","ags":"05913"}},{"attributes":{"cases7_Per_100k":422.922617880405,"last_Update":"17.01.2022, 00:00 Uhr","additionalProperties":{},"sn_V2":"00","gen":"Hagen","ags":"05914"}},{"attributes":{"cases7_Per_100k":493.387049009035,"last_Update":"17.01.2022, 00:00 Uhr","additionalProperties":{},"sn_V2":"00","gen":"Hamm","ags":"05915"}},{"attributes":{"cases7_Per_100k":616.159041671977,"last_Update":"17.01.2022, 00:00 Uhr","additionalProperties":{},"sn_V2":"00","gen":"Herne","ags":"05916"}},{"attributes":{"cases7_Per_100k":416.550614303841,"last_Update":"17.01.2022, 00:00 Uhr","additionalProperties":{},"sn_V2":"00","gen":"Ennepe-Ruhr-Kreis","ags":"05954"}},{"attributes":{"cases7_Per_100k":332.39393120488,"last_Update":"17.01.2022, 00:00 Uhr","additionalProperties":{},"sn_V2":"00","gen":"Hochsauerlandkreis","ags":"05958"}},{"attributes":{"cases7_Per_100k":548.619641659856,"last_Update":"17.01.2022, 00:00 Uhr","additionalProperties":{},"sn_V2":"00","gen":"Märkischer Kreis","ags":"05962"}},{"attributes":{"cases7_Per_100k":392.91552316252,"last_Update":"17.01.2022, 00:00 Uhr","additionalProperties":{},"sn_V2":"00","gen":"Olpe","ags":"05966"}},{"attributes":{"cases7_Per_100k":370.974006410373,"last_Update":"17.01.2022, 00:00 Uhr","additionalProperties":{},"sn_V2":"00","gen":"Siegen-Wittgenstein","ags":"05970"}},{"attributes":{"cases7_Per_100k":342.506710606745,"last_Update":"17.01.2022, 00:00 Uhr","additionalProperties":{},"sn_V2":"00","gen":"Soest","ags":"05974"}},{"attributes":{"cases7_Per_100k":422.490841374124,"last_Update":"17.01.2022, 00:00 Uhr","additionalProperties":{},"sn_V2":"00","gen":"Unna","ags":"05978"}},{"attributes":{"cases7_Per_100k":787.18886250267,"last_Update":"17.01.2022, 00:00 Uhr","additionalProperties":{},"sn_V2":"00","gen":"Darmstadt","ags":"06411"}},{"attributes":{"cases7_Per_100k":1060.06512202527,"last_Update":"17.01.2022, 00:00 Uhr","additionalProperties":{},"sn_V2":"00","gen":"Frankfurt am Main","ags":"06412"}},{"attributes":{"cases7_Per_100k":574.519451150567,"last_Update":"17.01.2022, 00:00 Uhr","additionalProperties":{},"sn_V2":"00","gen":"Offenbach am Main","ags":"06413"}},{"attributes":{"cases7_Per_100k":868.241873019177,"last_Update":"17.01.2022, 00:00 Uhr","additionalProperties":{},"sn_V2":"00","gen":"Wiesbaden","ags":"06414"}},{"attributes":{"cases7_Per_100k":525.432171651016,"last_Update":"17.01.2022, 00:00 Uhr","additionalProperties":{},"sn_V2":"00","gen":"Bergstraße","ags":"06431"}},{"attributes":{"cases7_Per_100k":728.919284785741,"last_Update":"17.01.2022, 00:00 Uhr","additionalProperties":{},"sn_V2":"00","gen":"Darmstadt-Dieburg","ags":"06432"}},{"attributes":{"cases7_Per_100k":669.308610731417,"last_Update":"17.01.2022, 00:00 Uhr","additionalProperties":{},"sn_V2":"00","gen":"Groß-Gerau","ags":"06433"}},{"attributes":{"cases7_Per_100k":917.477589861809,"last_Update":"17.01.2022, 00:00 Uhr","additionalProperties":{},"sn_V2":"00","gen":"Hochtaunuskreis","ags":"06434"}},{"attributes":{"cases7_Per_100k":502.503029483814,"last_Update":"17.01.2022, 00:00 Uhr","additionalProperties":{},"sn_V2":"00","gen":"Main-Kinzig-Kreis","ags":"06435"}},{"attributes":{"cases7_Per_100k":794.519860906781,"last_Update":"17.01.2022, 00:00 Uhr","additionalProperties":{},"sn_V2":"00","gen":"Main-Taunus-Kreis","ags":"06436"}},{"attributes":{"cases7_Per_100k":475.432540256734,"last_Update":"17.01.2022, 00:00 Uhr","additionalProperties":{},"sn_V2":"00","gen":"Odenwaldkreis","ags":"06437"}},{"attributes":{"cases7_Per_100k":552.249103892389,"last_Update":"17.01.2022, 00:00 Uhr","additionalProperties":{},"sn_V2":"00","gen":"Offenbach","ags":"06438"}},{"attributes":{"cases7_Per_100k":620.488387850592,"last_Update":"17.01.2022, 00:00 Uhr","additionalProperties":{},"sn_V2":"00","gen":"Rheingau-Taunus-Kreis","ags":"06439"}},{"attributes":{"cases7_Per_100k":603.506329888868,"last_Update":"17.01.2022, 00:00 Uhr","additionalProperties":{},"sn_V2":"00","gen":"Wetteraukreis","ags":"06440"}},{"attributes":{"cases7_Per_100k":456.441157740911,"last_Update":"17.01.2022, 00:00 Uhr","additionalProperties":{},"sn_V2":"00","gen":"Gießen","ags":"06531"}},{"attributes":{"cases7_Per_100k":415.592821650294,"last_Update":"17.01.2022, 00:00 Uhr","additionalProperties":{},"sn_V2":"00","gen":"Lahn-Dill-Kreis","ags":"06532"}},{"attributes":{"cases7_Per_100k":458.526562617896,"last_Update":"17.01.2022, 00:00 Uhr","additionalProperties":{},"sn_V2":"00","gen":"Limburg-Weilburg","ags":"06533"}},{"attributes":{"cases7_Per_100k":456.277475264637,"last_Update":"17.01.2022, 00:00 Uhr","additionalProperties":{},"sn_V2":"00","gen":"Marburg-Biedenkopf","ags":"06534"}},{"attributes":{"cases7_Per_100k":410.40319981802,"last_Update":"17.01.2022, 00:00 Uhr","additionalProperties":{},"sn_V2":"00","gen":"Vogelsbergkreis","ags":"06535"}},{"attributes":{"cases7_Per_100k":532.211213242609,"last_Update":"17.01.2022, 00:00 Uhr","additionalProperties":{},"sn_V2":"00","gen":"Kassel","ags":"06611"}},{"attributes":{"cases7_Per_100k":492.325903606355,"last_Update":"17.01.2022, 00:00 Uhr","additionalProperties":{},"sn_V2":"00","gen":"Fulda","ags":"06631"}},{"attributes":{"cases7_Per_100k":384.027131267456,"last_Update":"17.01.2022, 00:00 Uhr","additionalProperties":{},"sn_V2":"00","gen":"Hersfeld-Rotenburg","ags":"06632"}},{"attributes":{"cases7_Per_100k":351.888340850692,"last_Update":"17.01.2022, 00:00 Uhr","additionalProperties":{},"sn_V2":"00","gen":"Kassel","ags":"06633"}},{"attributes":{"cases7_Per_100k":400.355871886121,"last_Update":"17.01.2022, 00:00 Uhr","additionalProperties":{},"sn_V2":"00","gen":"Schwalm-Eder-Kreis","ags":"06634"}},{"attributes":{"cases7_Per_100k":466.370234079526,"last_Update":"17.01.2022, 00:00 Uhr","additionalProperties":{},"sn_V2":"00","gen":"Waldeck-Frankenberg","ags":"06635"}},{"attributes":{"cases7_Per_100k":263.878615836715,"last_Update":"17.01.2022, 00:00 Uhr","additionalProperties":{},"sn_V2":"00","gen":"Werra-Meißner-Kreis","ags":"06636"}},{"attributes":{"cases7_Per_100k":375.701132394962,"last_Update":"17.01.2022, 00:00 Uhr","additionalProperties":{},"sn_V2":"00","gen":"Koblenz","ags":"07111"}},{"attributes":{"cases7_Per_100k":339.518236651109,"last_Update":"17.01.2022, 00:00 Uhr","additionalProperties":{},"sn_V2":"00","gen":"Ahrweiler","ags":"07131"}},{"attributes":{"cases7_Per_100k":243.246802544021,"last_Update":"17.01.2022, 00:00 Uhr","additionalProperties":{},"sn_V2":"00","gen":"Altenkirchen (Westerwald)","ags":"07132"}},{"attributes":{"cases7_Per_100k":567.573356179053,"last_Update":"17.01.2022, 00:00 Uhr","additionalProperties":{},"sn_V2":"00","gen":"Bad Kreuznach","ags":"07133"}},{"attributes":{"cases7_Per_100k":458.987999505134,"last_Update":"17.01.2022, 00:00 Uhr","additionalProperties":{},"sn_V2":"00","gen":"Birkenfeld","ags":"07134"}},{"attributes":{"cases7_Per_100k":477.443242716555,"last_Update":"17.01.2022, 00:00 Uhr","additionalProperties":{},"sn_V2":"00","gen":"Cochem-Zell","ags":"07135"}},{"attributes":{"cases7_Per_100k":275.157598726174,"last_Update":"17.01.2022, 00:00 Uhr","additionalProperties":{},"sn_V2":"00","gen":"Mayen-Koblenz","ags":"07137"}},{"attributes":{"cases7_Per_100k":321.081630089936,"last_Update":"17.01.2022, 00:00 Uhr","additionalProperties":{},"sn_V2":"00","gen":"Neuwied","ags":"07138"}},{"attributes":{"cases7_Per_100k":429.396234078974,"last_Update":"17.01.2022, 00:00 Uhr","additionalProperties":{},"sn_V2":"00","gen":"Rhein-Hunsrück-Kreis","ags":"07140"}},{"attributes":{"cases7_Per_100k":377.731003312285,"last_Update":"17.01.2022, 00:00 Uhr","additionalProperties":{},"sn_V2":"00","gen":"Rhein-Lahn-Kreis","ags":"07141"}},{"attributes":{"cases7_Per_100k":213.479268352808,"last_Update":"17.01.2022, 00:00 Uhr","additionalProperties":{},"sn_V2":"00","gen":"Westerwaldkreis","ags":"07143"}},{"attributes":{"cases7_Per_100k":518.640331062399,"last_Update":"17.01.2022, 00:00 Uhr","additionalProperties":{},"sn_V2":"00","gen":"Trier","ags":"07211"}},{"attributes":{"cases7_Per_100k":391.356436082886,"last_Update":"17.01.2022, 00:00 Uhr","additionalProperties":{},"sn_V2":"00","gen":"Bernkastel-Wittlich","ags":"07231"}},{"attributes":{"cases7_Per_100k":420.768577282495,"last_Update":"17.01.2022, 00:00 Uhr","additionalProperties":{},"sn_V2":"00","gen":"Eifelkreis Bitburg-Prüm","ags":"07232"}},{"attributes":{"cases7_Per_100k":243.011357061381,"last_Update":"17.01.2022, 00:00 Uhr","additionalProperties":{},"sn_V2":"00","gen":"Vulkaneifel","ags":"07233"}},{"attributes":{"cases7_Per_100k":338.13183820159,"last_Update":"17.01.2022, 00:00 Uhr","additionalProperties":{},"sn_V2":"00","gen":"Trier-Saarburg","ags":"07235"}},{"attributes":{"cases7_Per_100k":352.820512820513,"last_Update":"17.01.2022, 00:00 Uhr","additionalProperties":{},"sn_V2":"00","gen":"Frankenthal (Pfalz)","ags":"07311"}},{"attributes":{"cases7_Per_100k":651.201059581385,"last_Update":"17.01.2022, 00:00 Uhr","additionalProperties":{},"sn_V2":"00","gen":"Kaiserslautern","ags":"07312"}},{"attributes":{"cases7_Per_100k":376.99475206169,"last_Update":"17.01.2022, 00:00 Uhr","additionalProperties":{},"sn_V2":"00","gen":"Landau in der Pfalz","ags":"07313"}},{"attributes":{"cases7_Per_100k":356.403970861802,"last_Update":"17.01.2022, 00:00 Uhr","additionalProperties":{},"sn_V2":"00","gen":"Ludwigshafen am Rhein","ags":"07314"}},{"attributes":{"cases7_Per_100k":565.57803641254,"last_Update":"17.01.2022, 00:00 Uhr","additionalProperties":{},"sn_V2":"00","gen":"Mainz","ags":"07315"}},{"attributes":{"cases7_Per_100k":243.874985930289,"last_Update":"17.01.2022, 00:00 Uhr","additionalProperties":{},"sn_V2":"00","gen":"Neustadt an der Weinstraße","ags":"07316"}},{"attributes":{"cases7_Per_100k":228.992433293509,"last_Update":"17.01.2022, 00:00 Uhr","additionalProperties":{},"sn_V2":"00","gen":"Pirmasens","ags":"07317"}},{"attributes":{"cases7_Per_100k":429.632841292052,"last_Update":"17.01.2022, 00:00 Uhr","additionalProperties":{},"sn_V2":"00","gen":"Speyer","ags":"07318"}},{"attributes":{"cases7_Per_100k":497.250146778658,"last_Update":"17.01.2022, 00:00 Uhr","additionalProperties":{},"sn_V2":"00","gen":"Worms","ags":"07319"}},{"attributes":{"cases7_Per_100k":273.521367018617,"last_Update":"17.01.2022, 00:00 Uhr","additionalProperties":{},"sn_V2":"00","gen":"Zweibrücken","ags":"07320"}},{"attributes":{"cases7_Per_100k":326.664881612669,"last_Update":"17.01.2022, 00:00 Uhr","additionalProperties":{},"sn_V2":"00","gen":"Alzey-Worms","ags":"07331"}},{"attributes":{"cases7_Per_100k":306.005834410995,"last_Update":"17.01.2022, 00:00 Uhr","additionalProperties":{},"sn_V2":"00","gen":"Bad Dürkheim","ags":"07332"}},{"attributes":{"cases7_Per_100k":325.659593057891,"last_Update":"17.01.2022, 00:00 Uhr","additionalProperties":{},"sn_V2":"00","gen":"Donnersbergkreis","ags":"07333"}},{"attributes":{"cases7_Per_100k":413.934235616948,"last_Update":"17.01.2022, 00:00 Uhr","additionalProperties":{},"sn_V2":"00","gen":"Germersheim","ags":"07334"}},{"attributes":{"cases7_Per_100k":522.009029345372,"last_Update":"17.01.2022, 00:00 Uhr","additionalProperties":{},"sn_V2":"00","gen":"Kaiserslautern","ags":"07335"}},{"attributes":{"cases7_Per_100k":310.962128236217,"last_Update":"17.01.2022, 00:00 Uhr","additionalProperties":{},"sn_V2":"00","gen":"Kusel","ags":"07336"}},{"attributes":{"cases7_Per_100k":265.383678001137,"last_Update":"17.01.2022, 00:00 Uhr","additionalProperties":{},"sn_V2":"00","gen":"Südliche Weinstraße","ags":"07337"}},{"attributes":{"cases7_Per_100k":286.906962017137,"last_Update":"17.01.2022, 00:00 Uhr","additionalProperties":{},"sn_V2":"00","gen":"Rhein-Pfalz-Kreis","ags":"07338"}},{"attributes":{"cases7_Per_100k":500.650041366269,"last_Update":"17.01.2022, 00:00 Uhr","additionalProperties":{},"sn_V2":"00","gen":"Mainz-Bingen","ags":"07339"}},{"attributes":{"cases7_Per_100k":163.309170600135,"last_Update":"17.01.2022, 00:00 Uhr","additionalProperties":{},"sn_V2":"00","gen":"Südwestpfalz","ags":"07340"}},{"attributes":{"cases7_Per_100k":536.724284275073,"last_Update":"17.01.2022, 00:00 Uhr","additionalProperties":{},"sn_V2":"00","gen":"Stuttgart","ags":"08111"}},{"attributes":{"cases7_Per_100k":552.051677534627,"last_Update":"17.01.2022, 00:00 Uhr","additionalProperties":{},"sn_V2":"00","gen":"Böblingen","ags":"08115"}},{"attributes":{"cases7_Per_100k":642.783119728195,"last_Update":"17.01.2022, 00:00 Uhr","additionalProperties":{},"sn_V2":"00","gen":"Esslingen","ags":"08116"}},{"attributes":{"cases7_Per_100k":450.960464639985,"last_Update":"17.01.2022, 00:00 Uhr","additionalProperties":{},"sn_V2":"00","gen":"Göppingen","ags":"08117"}},{"attributes":{"cases7_Per_100k":476.172126590222,"last_Update":"17.01.2022, 00:00 Uhr","additionalProperties":{},"sn_V2":"00","gen":"Ludwigsburg","ags":"08118"}},{"attributes":{"cases7_Per_100k":570.812055625506,"last_Update":"17.01.2022, 00:00 Uhr","additionalProperties":{},"sn_V2":"00","gen":"Rems-Murr-Kreis","ags":"08119"}},{"attributes":{"cases7_Per_100k":591.500735422037,"last_Update":"17.01.2022, 00:00 Uhr","additionalProperties":{},"sn_V2":"00","gen":"Heilbronn","ags":"08121"}},{"attributes":{"cases7_Per_100k":431.916804046622,"last_Update":"17.01.2022, 00:00 Uhr","additionalProperties":{},"sn_V2":"00","gen":"Heilbronn","ags":"08125"}},{"attributes":{"cases7_Per_100k":465.5699906886,"last_Update":"17.01.2022, 00:00 Uhr","additionalProperties":{},"sn_V2":"00","gen":"Hohenlohekreis","ags":"08126"}},{"attributes":{"cases7_Per_100k":405.337107045386,"last_Update":"17.01.2022, 00:00 Uhr","additionalProperties":{},"sn_V2":"00","gen":"Schwäbisch Hall","ags":"08127"}},{"attributes":{"cases7_Per_100k":455.970576708571,"last_Update":"17.01.2022, 00:00 Uhr","additionalProperties":{},"sn_V2":"00","gen":"Main-Tauber-Kreis","ags":"08128"}},{"attributes":{"cases7_Per_100k":505.978375448002,"last_Update":"17.01.2022, 00:00 Uhr","additionalProperties":{},"sn_V2":"00","gen":"Heidenheim","ags":"08135"}},{"attributes":{"cases7_Per_100k":420.30710099461,"last_Update":"17.01.2022, 00:00 Uhr","additionalProperties":{},"sn_V2":"00","gen":"Ostalbkreis","ags":"08136"}},{"attributes":{"cases7_Per_100k":816.966942595899,"last_Update":"17.01.2022, 00:00 Uhr","additionalProperties":{},"sn_V2":"00","gen":"Baden-Baden","ags":"08211"}},{"attributes":{"cases7_Per_100k":627.358674084737,"last_Update":"17.01.2022, 00:00 Uhr","additionalProperties":{},"sn_V2":"00","gen":"Karlsruhe","ags":"08212"}},{"attributes":{"cases7_Per_100k":467.940168109352,"last_Update":"17.01.2022, 00:00 Uhr","additionalProperties":{},"sn_V2":"00","gen":"Karlsruhe","ags":"08215"}},{"attributes":{"cases7_Per_100k":685.937843345929,"last_Update":"17.01.2022, 00:00 Uhr","additionalProperties":{},"sn_V2":"00","gen":"Rastatt","ags":"08216"}},{"attributes":{"cases7_Per_100k":540.503083639387,"last_Update":"17.01.2022, 00:00 Uhr","additionalProperties":{},"sn_V2":"00","gen":"Heidelberg","ags":"08221"}},{"attributes":{"cases7_Per_100k":656.720080330362,"last_Update":"17.01.2022, 00:00 Uhr","additionalProperties":{},"sn_V2":"00","gen":"Mannheim","ags":"08222"}},{"attributes":{"cases7_Per_100k":384.569914532292,"last_Update":"17.01.2022, 00:00 Uhr","additionalProperties":{},"sn_V2":"00","gen":"Neckar-Odenwald-Kreis","ags":"08225"}},{"attributes":{"cases7_Per_100k":431.750733720881,"last_Update":"17.01.2022, 00:00 Uhr","additionalProperties":{},"sn_V2":"00","gen":"Rhein-Neckar-Kreis","ags":"08226"}},{"attributes":{"cases7_Per_100k":600.717369222956,"last_Update":"17.01.2022, 00:00 Uhr","additionalProperties":{},"sn_V2":"00","gen":"Pforzheim","ags":"08231"}},{"attributes":{"cases7_Per_100k":488.919693535395,"last_Update":"17.01.2022, 00:00 Uhr","additionalProperties":{},"sn_V2":"00","gen":"Calw","ags":"08235"}},{"attributes":{"cases7_Per_100k":459.069245864872,"last_Update":"17.01.2022, 00:00 Uhr","additionalProperties":{},"sn_V2":"00","gen":"Enzkreis","ags":"08236"}},{"attributes":{"cases7_Per_100k":484.099895238417,"last_Update":"17.01.2022, 00:00 Uhr","additionalProperties":{},"sn_V2":"00","gen":"Freudenstadt","ags":"08237"}},{"attributes":{"cases7_Per_100k":743.050142894258,"last_Update":"17.01.2022, 00:00 Uhr","additionalProperties":{},"sn_V2":"00","gen":"Freiburg im Breisgau","ags":"08311"}},{"attributes":{"cases7_Per_100k":607.852242823757,"last_Update":"17.01.2022, 00:00 Uhr","additionalProperties":{},"sn_V2":"00","gen":"Breisgau-Hochschwarzwald","ags":"08315"}},{"attributes":{"cases7_Per_100k":578.921503997315,"last_Update":"17.01.2022, 00:00 Uhr","additionalProperties":{},"sn_V2":"00","gen":"Emmendingen","ags":"08316"}},{"attributes":{"cases7_Per_100k":579.777151047205,"last_Update":"17.01.2022, 00:00 Uhr","additionalProperties":{},"sn_V2":"00","gen":"Ortenaukreis","ags":"08317"}},{"attributes":{"cases7_Per_100k":659.218355378623,"last_Update":"17.01.2022, 00:00 Uhr","additionalProperties":{},"sn_V2":"00","gen":"Rottweil","ags":"08325"}},{"attributes":{"cases7_Per_100k":584.85850652035,"last_Update":"17.01.2022, 00:00 Uhr","additionalProperties":{},"sn_V2":"00","gen":"Schwarzwald-Baar-Kreis","ags":"08326"}},{"attributes":{"cases7_Per_100k":522.296410270888,"last_Update":"17.01.2022, 00:00 Uhr","additionalProperties":{},"sn_V2":"00","gen":"Tuttlingen","ags":"08327"}},{"attributes":{"cases7_Per_100k":525.314072979266,"last_Update":"17.01.2022, 00:00 Uhr","additionalProperties":{},"sn_V2":"00","gen":"Konstanz","ags":"08335"}},{"attributes":{"cases7_Per_100k":659.406927050104,"last_Update":"17.01.2022, 00:00 Uhr","additionalProperties":{},"sn_V2":"00","gen":"Lörrach","ags":"08336"}},{"attributes":{"cases7_Per_100k":623.696981376688,"last_Update":"17.01.2022, 00:00 Uhr","additionalProperties":{},"sn_V2":"00","gen":"Waldshut","ags":"08337"}},{"attributes":{"cases7_Per_100k":565.571119002981,"last_Update":"17.01.2022, 00:00 Uhr","additionalProperties":{},"sn_V2":"00","gen":"Reutlingen","ags":"08415"}},{"attributes":{"cases7_Per_100k":548.866158068201,"last_Update":"17.01.2022, 00:00 Uhr","additionalProperties":{},"sn_V2":"00","gen":"Tübingen","ags":"08416"}},{"attributes":{"cases7_Per_100k":494.56974012704,"last_Update":"17.01.2022, 00:00 Uhr","additionalProperties":{},"sn_V2":"00","gen":"Zollernalbkreis","ags":"08417"}},{"attributes":{"cases7_Per_100k":653.455163957122,"last_Update":"17.01.2022, 00:00 Uhr","additionalProperties":{},"sn_V2":"00","gen":"Ulm","ags":"08421"}},{"attributes":{"cases7_Per_100k":580.714819075296,"last_Update":"17.01.2022, 00:00 Uhr","additionalProperties":{},"sn_V2":"00","gen":"Alb-Donau-Kreis","ags":"08425"}},{"attributes":{"cases7_Per_100k":622.496909765142,"last_Update":"17.01.2022, 00:00 Uhr","additionalProperties":{},"sn_V2":"00","gen":"Biberach","ags":"08426"}},{"attributes":{"cases7_Per_100k":513.535963579791,"last_Update":"17.01.2022, 00:00 Uhr","additionalProperties":{},"sn_V2":"00","gen":"Bodenseekreis","ags":"08435"}},{"attributes":{"cases7_Per_100k":608.979740317887,"last_Update":"17.01.2022, 00:00 Uhr","additionalProperties":{},"sn_V2":"00","gen":"Ravensburg","ags":"08436"}},{"attributes":{"cases7_Per_100k":483.405373207276,"last_Update":"17.01.2022, 00:00 Uhr","additionalProperties":{},"sn_V2":"00","gen":"Sigmaringen","ags":"08437"}},{"attributes":{"cases7_Per_100k":865.996845610141,"last_Update":"17.01.2022, 00:00 Uhr","additionalProperties":{},"sn_V2":"00","gen":"Ingolstadt","ags":"09161"}},{"attributes":{"cases7_Per_100k":859.695122033165,"last_Update":"17.01.2022, 00:00 Uhr","additionalProperties":{},"sn_V2":"00","gen":"München","ags":"09162"}},{"attributes":{"cases7_Per_100k":713.937506879904,"last_Update":"17.01.2022, 00:00 Uhr","additionalProperties":{},"sn_V2":"00","gen":"Rosenheim","ags":"09163"}},{"attributes":{"cases7_Per_100k":489.906317731564,"last_Update":"17.01.2022, 00:00 Uhr","additionalProperties":{},"sn_V2":"00","gen":"Altötting","ags":"09171"}},{"attributes":{"cases7_Per_100k":429.806164003499,"last_Update":"17.01.2022, 00:00 Uhr","additionalProperties":{},"sn_V2":"00","gen":"Berchtesgadener Land","ags":"09172"}},{"attributes":{"cases7_Per_100k":828.315602283718,"last_Update":"17.01.2022, 00:00 Uhr","additionalProperties":{},"sn_V2":"00","gen":"Bad Tölz-Wolfratshausen","ags":"09173"}},{"attributes":{"cases7_Per_100k":795.528536524043,"last_Update":"17.01.2022, 00:00 Uhr","additionalProperties":{},"sn_V2":"00","gen":"Dachau","ags":"09174"}},{"attributes":{"cases7_Per_100k":826.560992705998,"last_Update":"17.01.2022, 00:00 Uhr","additionalProperties":{},"sn_V2":"00","gen":"Ebersberg","ags":"09175"}},{"attributes":{"cases7_Per_100k":523.395084441574,"last_Update":"17.01.2022, 00:00 Uhr","additionalProperties":{},"sn_V2":"00","gen":"Eichstätt","ags":"09176"}},{"attributes":{"cases7_Per_100k":674.629745627866,"last_Update":"17.01.2022, 00:00 Uhr","additionalProperties":{},"sn_V2":"00","gen":"Erding","ags":"09177"}},{"attributes":{"cases7_Per_100k":699.894073084026,"last_Update":"17.01.2022, 00:00 Uhr","additionalProperties":{},"sn_V2":"00","gen":"Freising","ags":"09178"}},{"attributes":{"cases7_Per_100k":730.547682179757,"last_Update":"17.01.2022, 00:00 Uhr","additionalProperties":{},"sn_V2":"00","gen":"Fürstenfeldbruck","ags":"09179"}},{"attributes":{"cases7_Per_100k":466.702160196649,"last_Update":"17.01.2022, 00:00 Uhr","additionalProperties":{},"sn_V2":"00","gen":"Garmisch-Partenkirchen","ags":"09180"}},{"attributes":{"cases7_Per_100k":601.558432973335,"last_Update":"17.01.2022, 00:00 Uhr","additionalProperties":{},"sn_V2":"00","gen":"Landsberg am Lech","ags":"09181"}},{"attributes":{"cases7_Per_100k":689.737779862851,"last_Update":"17.01.2022, 00:00 Uhr","additionalProperties":{},"sn_V2":"00","gen":"Miesbach","ags":"09182"}},{"attributes":{"cases7_Per_100k":597.512083308294,"last_Update":"17.01.2022, 00:00 Uhr","additionalProperties":{},"sn_V2":"00","gen":"Mühldorf a. Inn","ags":"09183"}},{"attributes":{"cases7_Per_100k":658.878705120323,"last_Update":"17.01.2022, 00:00 Uhr","additionalProperties":{},"sn_V2":"00","gen":"München","ags":"09184"}},{"attributes":{"cases7_Per_100k":585.285992018827,"last_Update":"17.01.2022, 00:00 Uhr","additionalProperties":{},"sn_V2":"00","gen":"Neuburg-Schrobenhausen","ags":"09185"}},{"attributes":{"cases7_Per_100k":580.81903227805,"last_Update":"17.01.2022, 00:00 Uhr","additionalProperties":{},"sn_V2":"00","gen":"Pfaffenhofen a.d. Ilm","ags":"09186"}},{"attributes":{"cases7_Per_100k":635.027376481062,"last_Update":"17.01.2022, 00:00 Uhr","additionalProperties":{},"sn_V2":"00","gen":"Rosenheim","ags":"09187"}},{"attributes":{"cases7_Per_100k":704.926432911207,"last_Update":"17.01.2022, 00:00 Uhr","additionalProperties":{},"sn_V2":"00","gen":"Starnberg","ags":"09188"}},{"attributes":{"cases7_Per_100k":438.910330450461,"last_Update":"17.01.2022, 00:00 Uhr","additionalProperties":{},"sn_V2":"00","gen":"Traunstein","ags":"09189"}},{"attributes":{"cases7_Per_100k":684.619566015837,"last_Update":"17.01.2022, 00:00 Uhr","additionalProperties":{},"sn_V2":"00","gen":"Weilheim-Schongau","ags":"09190"}},{"attributes":{"cases7_Per_100k":578.936563334018,"last_Update":"17.01.2022, 00:00 Uhr","additionalProperties":{},"sn_V2":"00","gen":"Landshut","ags":"09261"}},{"attributes":{"cases7_Per_100k":515.119717638081,"last_Update":"17.01.2022, 00:00 Uhr","additionalProperties":{},"sn_V2":"00","gen":"Passau","ags":"09262"}},{"attributes":{"cases7_Per_100k":430.563723431068,"last_Update":"17.01.2022, 00:00 Uhr","additionalProperties":{},"sn_V2":"00","gen":"Straubing","ags":"09263"}},{"attributes":{"cases7_Per_100k":334.786866311235,"last_Update":"17.01.2022, 00:00 Uhr","additionalProperties":{},"sn_V2":"00","gen":"Deggendorf","ags":"09271"}},{"attributes":{"cases7_Per_100k":242.486120860188,"last_Update":"17.01.2022, 00:00 Uhr","additionalProperties":{},"sn_V2":"00","gen":"Freyung-Grafenau","ags":"09272"}},{"attributes":{"cases7_Per_100k":394.683523786368,"last_Update":"17.01.2022, 00:00 Uhr","additionalProperties":{},"sn_V2":"00","gen":"Kelheim","ags":"09273"}},{"attributes":{"cases7_Per_100k":473.351489847448,"last_Update":"17.01.2022, 00:00 Uhr","additionalProperties":{},"sn_V2":"00","gen":"Landshut","ags":"09274"}},{"attributes":{"cases7_Per_100k":275.517694128837,"last_Update":"17.01.2022, 00:00 Uhr","additionalProperties":{},"sn_V2":"00","gen":"Passau","ags":"09275"}},{"attributes":{"cases7_Per_100k":451.41179361815,"last_Update":"17.01.2022, 00:00 Uhr","additionalProperties":{},"sn_V2":"00","gen":"Regen","ags":"09276"}},{"attributes":{"cases7_Per_100k":380.131362889984,"last_Update":"17.01.2022, 00:00 Uhr","additionalProperties":{},"sn_V2":"00","gen":"Rottal-Inn","ags":"09277"}},{"attributes":{"cases7_Per_100k":372.49987714384,"last_Update":"17.01.2022, 00:00 Uhr","additionalProperties":{},"sn_V2":"00","gen":"Straubing-Bogen","ags":"09278"}},{"attributes":{"cases7_Per_100k":430.874912591008,"last_Update":"17.01.2022, 00:00 Uhr","additionalProperties":{},"sn_V2":"00","gen":"Dingolfing-Landau","ags":"09279"}},{"attributes":{"cases7_Per_100k":392.371349757443,"last_Update":"17.01.2022, 00:00 Uhr","additionalProperties":{},"sn_V2":"00","gen":"Amberg","ags":"09361"}},{"attributes":{"cases7_Per_100k":702.042424640441,"last_Update":"17.01.2022, 00:00 Uhr","additionalProperties":{},"sn_V2":"00","gen":"Regensburg","ags":"09362"}},{"attributes":{"cases7_Per_100k":566.592218173269,"last_Update":"17.01.2022, 00:00 Uhr","additionalProperties":{},"sn_V2":"00","gen":"Weiden i.d. OPf.","ags":"09363"}},{"attributes":{"cases7_Per_100k":342.725101458281,"last_Update":"17.01.2022, 00:00 Uhr","additionalProperties":{},"sn_V2":"00","gen":"Amberg-Sulzbach","ags":"09371"}},{"attributes":{"cases7_Per_100k":397.364435492685,"last_Update":"17.01.2022, 00:00 Uhr","additionalProperties":{},"sn_V2":"00","gen":"Cham","ags":"09372"}},{"attributes":{"cases7_Per_100k":175.263449805879,"last_Update":"17.01.2022, 00:00 Uhr","additionalProperties":{},"sn_V2":"00","gen":"Neumarkt i.d. OPf.","ags":"09373"}},{"attributes":{"cases7_Per_100k":372.972687410851,"last_Update":"17.01.2022, 00:00 Uhr","additionalProperties":{},"sn_V2":"00","gen":"Neustadt a.d. Waldnaab","ags":"09374"}},{"attributes":{"cases7_Per_100k":529.661562218505,"last_Update":"17.01.2022, 00:00 Uhr","additionalProperties":{},"sn_V2":"00","gen":"Regensburg","ags":"09375"}},{"attributes":{"cases7_Per_100k":346.855068461782,"last_Update":"17.01.2022, 00:00 Uhr","additionalProperties":{},"sn_V2":"00","gen":"Schwandorf","ags":"09376"}},{"attributes":{"cases7_Per_100k":492.356616826601,"last_Update":"17.01.2022, 00:00 Uhr","additionalProperties":{},"sn_V2":"00","gen":"Tirschenreuth","ags":"09377"}},{"attributes":{"cases7_Per_100k":374.312022328299,"last_Update":"17.01.2022, 00:00 Uhr","additionalProperties":{},"sn_V2":"00","gen":"Bamberg","ags":"09461"}},{"attributes":{"cases7_Per_100k":542.891097666379,"last_Update":"17.01.2022, 00:00 Uhr","additionalProperties":{},"sn_V2":"00","gen":"Bayreuth","ags":"09462"}},{"attributes":{"cases7_Per_100k":406.444346506048,"last_Update":"17.01.2022, 00:00 Uhr","additionalProperties":{},"sn_V2":"00","gen":"Coburg","ags":"09463"}},{"attributes":{"cases7_Per_100k":436.101210900317,"last_Update":"17.01.2022, 00:00 Uhr","additionalProperties":{},"sn_V2":"00","gen":"Hof","ags":"09464"}},{"attributes":{"cases7_Per_100k":400.008135758693,"last_Update":"17.01.2022, 00:00 Uhr","additionalProperties":{},"sn_V2":"00","gen":"Bamberg","ags":"09471"}},{"attributes":{"cases7_Per_100k":356.870725990799,"last_Update":"17.01.2022, 00:00 Uhr","additionalProperties":{},"sn_V2":"00","gen":"Bayreuth","ags":"09472"}},{"attributes":{"cases7_Per_100k":180.198911875801,"last_Update":"17.01.2022, 00:00 Uhr","additionalProperties":{},"sn_V2":"00","gen":"Coburg","ags":"09473"}},{"attributes":{"cases7_Per_100k":462.264150943396,"last_Update":"17.01.2022, 00:00 Uhr","additionalProperties":{},"sn_V2":"00","gen":"Forchheim","ags":"09474"}},{"attributes":{"cases7_Per_100k":343.835297602675,"last_Update":"17.01.2022, 00:00 Uhr","additionalProperties":{},"sn_V2":"00","gen":"Hof","ags":"09475"}},{"attributes":{"cases7_Per_100k":245.64840629945,"last_Update":"17.01.2022, 00:00 Uhr","additionalProperties":{},"sn_V2":"00","gen":"Kronach","ags":"09476"}},{"attributes":{"cases7_Per_100k":460.603684829479,"last_Update":"17.01.2022, 00:00 Uhr","additionalProperties":{},"sn_V2":"00","gen":"Kulmbach","ags":"09477"}},{"attributes":{"cases7_Per_100k":446.629297682923,"last_Update":"17.01.2022, 00:00 Uhr","additionalProperties":{},"sn_V2":"00","gen":"Lichtenfels","ags":"09478"}},{"attributes":{"cases7_Per_100k":258.426654069525,"last_Update":"17.01.2022, 00:00 Uhr","additionalProperties":{},"sn_V2":"00","gen":"Wunsiedel i. Fichtelgebirge","ags":"09479"}},{"attributes":{"cases7_Per_100k":417.45639500012,"last_Update":"17.01.2022, 00:00 Uhr","additionalProperties":{},"sn_V2":"00","gen":"Ansbach","ags":"09561"}},{"attributes":{"cases7_Per_100k":614.850736308226,"last_Update":"17.01.2022, 00:00 Uhr","additionalProperties":{},"sn_V2":"00","gen":"Erlangen","ags":"09562"}},{"attributes":{"cases7_Per_100k":481.972812989869,"last_Update":"17.01.2022, 00:00 Uhr","additionalProperties":{},"sn_V2":"00","gen":"Fürth","ags":"09563"}},{"attributes":{"cases7_Per_100k":429.450113763546,"last_Update":"17.01.2022, 00:00 Uhr","additionalProperties":{},"sn_V2":"00","gen":"Nürnberg","ags":"09564"}},{"attributes":{"cases7_Per_100k":462.782540919719,"last_Update":"17.01.2022, 00:00 Uhr","additionalProperties":{},"sn_V2":"00","gen":"Schwabach","ags":"09565"}},{"attributes":{"cases7_Per_100k":302.186535431371,"last_Update":"17.01.2022, 00:00 Uhr","additionalProperties":{},"sn_V2":"00","gen":"Ansbach","ags":"09571"}},{"attributes":{"cases7_Per_100k":523.514717063104,"last_Update":"17.01.2022, 00:00 Uhr","additionalProperties":{},"sn_V2":"00","gen":"Erlangen-Höchstadt","ags":"09572"}},{"attributes":{"cases7_Per_100k":425.460213151354,"last_Update":"17.01.2022, 00:00 Uhr","additionalProperties":{},"sn_V2":"00","gen":"Fürth","ags":"09573"}},{"attributes":{"cases7_Per_100k":451.669072062544,"last_Update":"17.01.2022, 00:00 Uhr","additionalProperties":{},"sn_V2":"00","gen":"Nürnberger Land","ags":"09574"}},{"attributes":{"cases7_Per_100k":301.16912868315,"last_Update":"17.01.2022, 00:00 Uhr","additionalProperties":{},"sn_V2":"00","gen":"Neustadt a.d. Aisch-Bad Windsheim","ags":"09575"}},{"attributes":{"cases7_Per_100k":371.948917966784,"last_Update":"17.01.2022, 00:00 Uhr","additionalProperties":{},"sn_V2":"00","gen":"Roth","ags":"09576"}},{"attributes":{"cases7_Per_100k":432.099414405417,"last_Update":"17.01.2022, 00:00 Uhr","additionalProperties":{},"sn_V2":"00","gen":"Weißenburg-Gunzenhausen","ags":"09577"}},{"attributes":{"cases7_Per_100k":469.953992492026,"last_Update":"17.01.2022, 00:00 Uhr","additionalProperties":{},"sn_V2":"00","gen":"Aschaffenburg","ags":"09661"}},{"attributes":{"cases7_Per_100k":742.699600517639,"last_Update":"17.01.2022, 00:00 Uhr","additionalProperties":{},"sn_V2":"00","gen":"Schweinfurt","ags":"09662"}},{"attributes":{"cases7_Per_100k":690.801392630402,"last_Update":"17.01.2022, 00:00 Uhr","additionalProperties":{},"sn_V2":"00","gen":"Würzburg","ags":"09663"}},{"attributes":{"cases7_Per_100k":399.638149984541,"last_Update":"17.01.2022, 00:00 Uhr","additionalProperties":{},"sn_V2":"00","gen":"Aschaffenburg","ags":"09671"}},{"attributes":{"cases7_Per_100k":508.873789607343,"last_Update":"17.01.2022, 00:00 Uhr","additionalProperties":{},"sn_V2":"00","gen":"Bad Kissingen","ags":"09672"}},{"attributes":{"cases7_Per_100k":562.193434788077,"last_Update":"17.01.2022, 00:00 Uhr","additionalProperties":{},"sn_V2":"00","gen":"Rhön-Grabfeld","ags":"09673"}},{"attributes":{"cases7_Per_100k":408.187481459508,"last_Update":"17.01.2022, 00:00 Uhr","additionalProperties":{},"sn_V2":"00","gen":"Haßberge","ags":"09674"}},{"attributes":{"cases7_Per_100k":474.39364857791,"last_Update":"17.01.2022, 00:00 Uhr","additionalProperties":{},"sn_V2":"00","gen":"Kitzingen","ags":"09675"}},{"attributes":{"cases7_Per_100k":591.876839905859,"last_Update":"17.01.2022, 00:00 Uhr","additionalProperties":{},"sn_V2":"00","gen":"Miltenberg","ags":"09676"}},{"attributes":{"cases7_Per_100k":426.271670794437,"last_Update":"17.01.2022, 00:00 Uhr","additionalProperties":{},"sn_V2":"00","gen":"Main-Spessart","ags":"09677"}},{"attributes":{"cases7_Per_100k":504.098502403763,"last_Update":"17.01.2022, 00:00 Uhr","additionalProperties":{},"sn_V2":"00","gen":"Schweinfurt","ags":"09678"}},{"attributes":{"cases7_Per_100k":452.989299126597,"last_Update":"17.01.2022, 00:00 Uhr","additionalProperties":{},"sn_V2":"00","gen":"Würzburg","ags":"09679"}},{"attributes":{"cases7_Per_100k":641.584693912044,"last_Update":"17.01.2022, 00:00 Uhr","additionalProperties":{},"sn_V2":"00","gen":"Augsburg","ags":"09761"}},{"attributes":{"cases7_Per_100k":550.803815323989,"last_Update":"17.01.2022, 00:00 Uhr","additionalProperties":{},"sn_V2":"00","gen":"Kaufbeuren","ags":"09762"}},{"attributes":{"cases7_Per_100k":587.467362924282,"last_Update":"17.01.2022, 00:00 Uhr","additionalProperties":{},"sn_V2":"00","gen":"Kempten (Allgäu)","ags":"09763"}},{"attributes":{"cases7_Per_100k":462.128043282236,"last_Update":"17.01.2022, 00:00 Uhr","additionalProperties":{},"sn_V2":"00","gen":"Memmingen","ags":"09764"}},{"attributes":{"cases7_Per_100k":591.006043370068,"last_Update":"17.01.2022, 00:00 Uhr","additionalProperties":{},"sn_V2":"00","gen":"Aichach-Friedberg","ags":"09771"}},{"attributes":{"cases7_Per_100k":496.678389996092,"last_Update":"17.01.2022, 00:00 Uhr","additionalProperties":{},"sn_V2":"00","gen":"Augsburg","ags":"09772"}},{"attributes":{"cases7_Per_100k":344.749516321574,"last_Update":"17.01.2022, 00:00 Uhr","additionalProperties":{},"sn_V2":"00","gen":"Dillingen a.d. Donau","ags":"09773"}},{"attributes":{"cases7_Per_100k":542.633223916697,"last_Update":"17.01.2022, 00:00 Uhr","additionalProperties":{},"sn_V2":"00","gen":"Günzburg","ags":"09774"}},{"attributes":{"cases7_Per_100k":506.759638955086,"last_Update":"17.01.2022, 00:00 Uhr","additionalProperties":{},"sn_V2":"00","gen":"Neu-Ulm","ags":"09775"}},{"attributes":{"cases7_Per_100k":774.806602911616,"last_Update":"17.01.2022, 00:00 Uhr","additionalProperties":{},"sn_V2":"00","gen":"Lindau (Bodensee)","ags":"09776"}},{"attributes":{"cases7_Per_100k":719.485296708408,"last_Update":"17.01.2022, 00:00 Uhr","additionalProperties":{},"sn_V2":"00","gen":"Ostallgäu","ags":"09777"}},{"attributes":{"cases7_Per_100k":552.803699953477,"last_Update":"17.01.2022, 00:00 Uhr","additionalProperties":{},"sn_V2":"00","gen":"Unterallgäu","ags":"09778"}},{"attributes":{"cases7_Per_100k":437.003067210625,"last_Update":"17.01.2022, 00:00 Uhr","additionalProperties":{},"sn_V2":"00","gen":"Donau-Ries","ags":"09779"}},{"attributes":{"cases7_Per_100k":473.424264912864,"last_Update":"17.01.2022, 00:00 Uhr","additionalProperties":{},"sn_V2":"00","gen":"Oberallgäu","ags":"09780"}},{"attributes":{"cases7_Per_100k":643.049508094607,"last_Update":"17.01.2022, 00:00 Uhr","additionalProperties":{},"sn_V2":"00","gen":"Regionalverband Saarbrücken","ags":"10041"}},{"attributes":{"cases7_Per_100k":458.099370838206,"last_Update":"17.01.2022, 00:00 Uhr","additionalProperties":{},"sn_V2":"00","gen":"Merzig-Wadern","ags":"10042"}},{"attributes":{"cases7_Per_100k":319.427926691672,"last_Update":"17.01.2022, 00:00 Uhr","additionalProperties":{},"sn_V2":"00","gen":"Neunkirchen","ags":"10043"}},{"attributes":{"cases7_Per_100k":449.073978485743,"last_Update":"17.01.2022, 00:00 Uhr","additionalProperties":{},"sn_V2":"00","gen":"Saarlouis","ags":"10044"}},{"attributes":{"cases7_Per_100k":354.379623877563,"last_Update":"17.01.2022, 00:00 Uhr","additionalProperties":{},"sn_V2":"00","gen":"Saarpfalz-Kreis","ags":"10045"}},{"attributes":{"cases7_Per_100k":382.844849522311,"last_Update":"17.01.2022, 00:00 Uhr","additionalProperties":{},"sn_V2":"00","gen":"St. Wendel","ags":"10046"}},{"attributes":{"cases7_Per_100k":388.672959466963,"last_Update":"17.01.2022, 00:00 Uhr","additionalProperties":{},"sn_V2":"00","gen":"Brandenburg an der Havel","ags":"12051"}},{"attributes":{"cases7_Per_100k":487.369924918687,"last_Update":"17.01.2022, 00:00 Uhr","additionalProperties":{},"sn_V2":"00","gen":"Cottbus","ags":"12052"}},{"attributes":{"cases7_Per_100k":426.20363062352,"last_Update":"17.01.2022, 00:00 Uhr","additionalProperties":{},"sn_V2":"00","gen":"Frankfurt (Oder)","ags":"12053"}},{"attributes":{"cases7_Per_100k":874.736425935688,"last_Update":"17.01.2022, 00:00 Uhr","additionalProperties":{},"sn_V2":"00","gen":"Potsdam","ags":"12054"}},{"attributes":{"cases7_Per_100k":559.40173905617,"last_Update":"17.01.2022, 00:00 Uhr","additionalProperties":{},"sn_V2":"00","gen":"Barnim","ags":"12060"}},{"attributes":{"cases7_Per_100k":503.704216575504,"last_Update":"17.01.2022, 00:00 Uhr","additionalProperties":{},"sn_V2":"00","gen":"Dahme-Spreewald","ags":"12061"}},{"attributes":{"cases7_Per_100k":232.477617846367,"last_Update":"17.01.2022, 00:00 Uhr","additionalProperties":{},"sn_V2":"00","gen":"Elbe-Elster","ags":"12062"}},{"attributes":{"cases7_Per_100k":887.105098577353,"last_Update":"17.01.2022, 00:00 Uhr","additionalProperties":{},"sn_V2":"00","gen":"Havelland","ags":"12063"}},{"attributes":{"cases7_Per_100k":536.524759755572,"last_Update":"17.01.2022, 00:00 Uhr","additionalProperties":{},"sn_V2":"00","gen":"Märkisch-Oderland","ags":"12064"}},{"attributes":{"cases7_Per_100k":627.351400804728,"last_Update":"17.01.2022, 00:00 Uhr","additionalProperties":{},"sn_V2":"00","gen":"Oberhavel","ags":"12065"}},{"attributes":{"cases7_Per_100k":265.69246097642,"last_Update":"17.01.2022, 00:00 Uhr","additionalProperties":{},"sn_V2":"00","gen":"Oberspreewald-Lausitz","ags":"12066"}},{"attributes":{"cases7_Per_100k":751.913251076552,"last_Update":"17.01.2022, 00:00 Uhr","additionalProperties":{},"sn_V2":"00","gen":"Oder-Spree","ags":"12067"}},{"attributes":{"cases7_Per_100k":441.259817018865,"last_Update":"17.01.2022, 00:00 Uhr","additionalProperties":{},"sn_V2":"00","gen":"Ostprignitz-Ruppin","ags":"12068"}},{"attributes":{"cases7_Per_100k":570.303825577874,"last_Update":"17.01.2022, 00:00 Uhr","additionalProperties":{},"sn_V2":"00","gen":"Potsdam-Mittelmark","ags":"12069"}},{"attributes":{"cases7_Per_100k":505.939865433137,"last_Update":"17.01.2022, 00:00 Uhr","additionalProperties":{},"sn_V2":"00","gen":"Prignitz","ags":"12070"}},{"attributes":{"cases7_Per_100k":352.178106555999,"last_Update":"17.01.2022, 00:00 Uhr","additionalProperties":{},"sn_V2":"00","gen":"Spree-Neiße","ags":"12071"}},{"attributes":{"cases7_Per_100k":800.913997924852,"last_Update":"17.01.2022, 00:00 Uhr","additionalProperties":{},"sn_V2":"00","gen":"Teltow-Fläming","ags":"12072"}},{"attributes":{"cases7_Per_100k":516.701902748414,"last_Update":"17.01.2022, 00:00 Uhr","additionalProperties":{},"sn_V2":"00","gen":"Uckermark","ags":"12073"}},{"attributes":{"cases7_Per_100k":445.802899632165,"last_Update":"17.01.2022, 00:00 Uhr","additionalProperties":{},"sn_V2":"00","gen":"Rostock","ags":"13003"}},{"attributes":{"cases7_Per_100k":516.687759520547,"last_Update":"17.01.2022, 00:00 Uhr","additionalProperties":{},"sn_V2":"00","gen":"Schwerin","ags":"13004"}},{"attributes":{"cases7_Per_100k":449.12558078254,"last_Update":"17.01.2022, 00:00 Uhr","additionalProperties":{},"sn_V2":"00","gen":"Mecklenburgische Seenplatte","ags":"13071"}},{"attributes":{"cases7_Per_100k":368.541313481241,"last_Update":"17.01.2022, 00:00 Uhr","additionalProperties":{},"sn_V2":"00","gen":"Rostock","ags":"13072"}},{"attributes":{"cases7_Per_100k":368.705714273037,"last_Update":"17.01.2022, 00:00 Uhr","additionalProperties":{},"sn_V2":"00","gen":"Vorpommern-Rügen","ags":"13073"}},{"attributes":{"cases7_Per_100k":712.137996518436,"last_Update":"17.01.2022, 00:00 Uhr","additionalProperties":{},"sn_V2":"00","gen":"Nordwestmecklenburg","ags":"13074"}},{"attributes":{"cases7_Per_100k":375.361046430253,"last_Update":"17.01.2022, 00:00 Uhr","additionalProperties":{},"sn_V2":"00","gen":"Vorpommern-Greifswald","ags":"13075"}},{"attributes":{"cases7_Per_100k":613.659107645248,"last_Update":"17.01.2022, 00:00 Uhr","additionalProperties":{},"sn_V2":"00","gen":"Ludwigslust-Parchim","ags":"13076"}},{"attributes":{"cases7_Per_100k":148.117233562874,"last_Update":"17.01.2022, 00:00 Uhr","additionalProperties":{},"sn_V2":"00","gen":"Chemnitz","ags":"14511"}},{"attributes":{"cases7_Per_100k":152.44775049184,"last_Update":"17.01.2022, 00:00 Uhr","additionalProperties":{},"sn_V2":"00","gen":"Erzgebirgskreis","ags":"14521"}},{"attributes":{"cases7_Per_100k":206.651319848478,"last_Update":"17.01.2022, 00:00 Uhr","additionalProperties":{},"sn_V2":"00","gen":"Mittelsachsen","ags":"14522"}},{"attributes":{"cases7_Per_100k":112.101114311873,"last_Update":"17.01.2022, 00:00 Uhr","additionalProperties":{},"sn_V2":"00","gen":"Vogtlandkreis","ags":"14523"}},{"attributes":{"cases7_Per_100k":157.355151538459,"last_Update":"17.01.2022, 00:00 Uhr","additionalProperties":{},"sn_V2":"00","gen":"Zwickau","ags":"14524"}},{"attributes":{"cases7_Per_100k":346.261508341019,"last_Update":"17.01.2022, 00:00 Uhr","additionalProperties":{},"sn_V2":"00","gen":"Dresden","ags":"14612"}},{"attributes":{"cases7_Per_100k":209.388946679642,"last_Update":"17.01.2022, 00:00 Uhr","additionalProperties":{},"sn_V2":"00","gen":"Bautzen","ags":"14625"}},{"attributes":{"cases7_Per_100k":212.725197359494,"last_Update":"17.01.2022, 00:00 Uhr","additionalProperties":{},"sn_V2":"00","gen":"Görlitz","ags":"14626"}},{"attributes":{"cases7_Per_100k":279.983858285733,"last_Update":"17.01.2022, 00:00 Uhr","additionalProperties":{},"sn_V2":"00","gen":"Meißen","ags":"14627"}},{"attributes":{"cases7_Per_100k":250.488309183482,"last_Update":"17.01.2022, 00:00 Uhr","additionalProperties":{},"sn_V2":"00","gen":"Sächsische Schweiz-Osterzgebirge","ags":"14628"}},{"attributes":{"cases7_Per_100k":376.238717441041,"last_Update":"17.01.2022, 00:00 Uhr","additionalProperties":{},"sn_V2":"00","gen":"Leipzig","ags":"14713"}},{"attributes":{"cases7_Per_100k":279.813921806909,"last_Update":"17.01.2022, 00:00 Uhr","additionalProperties":{},"sn_V2":"00","gen":"Leipzig","ags":"14729"}},{"attributes":{"cases7_Per_100k":257.794615182026,"last_Update":"17.01.2022, 00:00 Uhr","additionalProperties":{},"sn_V2":"00","gen":"Nordsachsen","ags":"14730"}},{"attributes":{"cases7_Per_100k":258.336063714495,"last_Update":"17.01.2022, 00:00 Uhr","additionalProperties":{},"sn_V2":"00","gen":"Dessau-Roßlau","ags":"15001"}},{"attributes":{"cases7_Per_100k":387.19441700124,"last_Update":"17.01.2022, 00:00 Uhr","additionalProperties":{},"sn_V2":"00","gen":"Halle (Saale)","ags":"15002"}},{"attributes":{"cases7_Per_100k":376.206128724419,"last_Update":"17.01.2022, 00:00 Uhr","additionalProperties":{},"sn_V2":"00","gen":"Magdeburg","ags":"15003"}},{"attributes":{"cases7_Per_100k":303.554367675693,"last_Update":"17.01.2022, 00:00 Uhr","additionalProperties":{},"sn_V2":"00","gen":"Altmarkkreis Salzwedel","ags":"15081"}},{"attributes":{"cases7_Per_100k":248.700840239923,"last_Update":"17.01.2022, 00:00 Uhr","additionalProperties":{},"sn_V2":"00","gen":"Anhalt-Bitterfeld","ags":"15082"}},{"attributes":{"cases7_Per_100k":303.10669707505,"last_Update":"17.01.2022, 00:00 Uhr","additionalProperties":{},"sn_V2":"00","gen":"Börde","ags":"15083"}},{"attributes":{"cases7_Per_100k":202.714116785855,"last_Update":"17.01.2022, 00:00 Uhr","additionalProperties":{},"sn_V2":"00","gen":"Burgenlandkreis","ags":"15084"}},{"attributes":{"cases7_Per_100k":209.503495674843,"last_Update":"17.01.2022, 00:00 Uhr","additionalProperties":{},"sn_V2":"00","gen":"Harz","ags":"15085"}},{"attributes":{"cases7_Per_100k":336.677740120578,"last_Update":"17.01.2022, 00:00 Uhr","additionalProperties":{},"sn_V2":"00","gen":"Jerichower Land","ags":"15086"}},{"attributes":{"cases7_Per_100k":192.983768419478,"last_Update":"17.01.2022, 00:00 Uhr","additionalProperties":{},"sn_V2":"00","gen":"Mansfeld-Südharz","ags":"15087"}},{"attributes":{"cases7_Per_100k":322.186726561052,"last_Update":"17.01.2022, 00:00 Uhr","additionalProperties":{},"sn_V2":"00","gen":"Saalekreis","ags":"15088"}},{"attributes":{"cases7_Per_100k":241.655419642905,"last_Update":"17.01.2022, 00:00 Uhr","additionalProperties":{},"sn_V2":"00","gen":"Salzlandkreis","ags":"15089"}},{"attributes":{"cases7_Per_100k":276.960673394578,"last_Update":"17.01.2022, 00:00 Uhr","additionalProperties":{},"sn_V2":"00","gen":"Stendal","ags":"15090"}},{"attributes":{"cases7_Per_100k":186.012803478681,"last_Update":"17.01.2022, 00:00 Uhr","additionalProperties":{},"sn_V2":"00","gen":"Wittenberg","ags":"15091"}},{"attributes":{"cases7_Per_100k":232.577728693634,"last_Update":"17.01.2022, 00:00 Uhr","additionalProperties":{},"sn_V2":"00","gen":"Erfurt","ags":"16051"}},{"attributes":{"cases7_Per_100k":181.273473286586,"last_Update":"17.01.2022, 00:00 Uhr","additionalProperties":{},"sn_V2":"00","gen":"Gera","ags":"16052"}},{"attributes":{"cases7_Per_100k":333.240014088196,"last_Update":"17.01.2022, 00:00 Uhr","additionalProperties":{},"sn_V2":"00","gen":"Jena","ags":"16053"}},{"attributes":{"cases7_Per_100k":230.800934194257,"last_Update":"17.01.2022, 00:00 Uhr","additionalProperties":{},"sn_V2":"00","gen":"Suhl","ags":"16054"}},{"attributes":{"cases7_Per_100k":251.927862607146,"last_Update":"17.01.2022, 00:00 Uhr","additionalProperties":{},"sn_V2":"00","gen":"Weimar","ags":"16055"}},{"attributes":{"cases7_Per_100k":232.247167288338,"last_Update":"17.01.2022, 00:00 Uhr","additionalProperties":{},"sn_V2":"00","gen":"Eichsfeld","ags":"16061"}},{"attributes":{"cases7_Per_100k":211.021635781508,"last_Update":"17.01.2022, 00:00 Uhr","additionalProperties":{},"sn_V2":"00","gen":"Nordhausen","ags":"16062"}},{"attributes":{"cases7_Per_100k":250.723722465721,"last_Update":"17.01.2022, 00:00 Uhr","additionalProperties":{},"sn_V2":"00","gen":"Wartburgkreis","ags":"16063"}},{"attributes":{"cases7_Per_100k":239.926055576314,"last_Update":"17.01.2022, 00:00 Uhr","additionalProperties":{},"sn_V2":"00","gen":"Unstrut-Hainich-Kreis","ags":"16064"}},{"attributes":{"cases7_Per_100k":204.02056527298,"last_Update":"17.01.2022, 00:00 Uhr","additionalProperties":{},"sn_V2":"00","gen":"Kyffhäuserkreis","ags":"16065"}},{"attributes":{"cases7_Per_100k":165.001891485098,"last_Update":"17.01.2022, 00:00 Uhr","additionalProperties":{},"sn_V2":"00","gen":"Schmalkalden-Meiningen","ags":"16066"}},{"attributes":{"cases7_Per_100k":135.252632595884,"last_Update":"17.01.2022, 00:00 Uhr","additionalProperties":{},"sn_V2":"00","gen":"Gotha","ags":"16067"}},{"attributes":{"cases7_Per_100k":130.232827354682,"last_Update":"17.01.2022, 00:00 Uhr","additionalProperties":{},"sn_V2":"00","gen":"Sömmerda","ags":"16068"}},{"attributes":{"cases7_Per_100k":213.866189989785,"last_Update":"17.01.2022, 00:00 Uhr","additionalProperties":{},"sn_V2":"00","gen":"Hildburghausen","ags":"16069"}},{"attributes":{"cases7_Per_100k":196.958506145484,"last_Update":"17.01.2022, 00:00 Uhr","additionalProperties":{},"sn_V2":"00","gen":"Ilm-Kreis","ags":"16070"}},{"attributes":{"cases7_Per_100k":230.887946433996,"last_Update":"17.01.2022, 00:00 Uhr","additionalProperties":{},"sn_V2":"00","gen":"Weimarer Land","ags":"16071"}},{"attributes":{"cases7_Per_100k":131.477455998878,"last_Update":"17.01.2022, 00:00 Uhr","additionalProperties":{},"sn_V2":"00","gen":"Sonneberg","ags":"16072"}},{"attributes":{"cases7_Per_100k":160.565503872174,"last_Update":"17.01.2022, 00:00 Uhr","additionalProperties":{},"sn_V2":"00","gen":"Saalfeld-Rudolstadt","ags":"16073"}},{"attributes":{"cases7_Per_100k":189.576893353941,"last_Update":"17.01.2022, 00:00 Uhr","additionalProperties":{},"sn_V2":"00","gen":"Saale-Holzland-Kreis","ags":"16074"}},{"attributes":{"cases7_Per_100k":109.252561784207,"last_Update":"17.01.2022, 00:00 Uhr","additionalProperties":{},"sn_V2":"00","gen":"Saale-Orla-Kreis","ags":"16075"}},{"attributes":{"cases7_Per_100k":94.1366325981711,"last_Update":"17.01.2022, 00:00 Uhr","additionalProperties":{},"sn_V2":"00","gen":"Greiz","ags":"16076"}},{"attributes":{"cases7_Per_100k":148.263841731178,"last_Update":"17.01.2022, 00:00 Uhr","additionalProperties":{},"sn_V2":"00","gen":"Altenburger Land","ags":"16077"}},{"attributes":{"cases7_Per_100k":1179.73201909749,"last_Update":"17.01.2022, 00:00 Uhr","additionalProperties":{},"sn_V2":null,"gen":"Berlin Reinickendorf","ags":null}},{"attributes":{"cases7_Per_100k":913.912017784918,"last_Update":"17.01.2022, 00:00 Uhr","additionalProperties":{},"sn_V2":null,"gen":"Berlin Charlottenburg-Wilmersdorf","ags":null}},{"attributes":{"cases7_Per_100k":815.0421990388,"last_Update":"17.01.2022, 00:00 Uhr","additionalProperties":{},"sn_V2":null,"gen":"Berlin Treptow-Köpenick","ags":null}},{"attributes":{"cases7_Per_100k":831.545794397148,"last_Update":"17.01.2022, 00:00 Uhr","additionalProperties":{},"sn_V2":null,"gen":"Berlin Pankow","ags":null}},{"attributes":{"cases7_Per_100k":1374.21548527671,"last_Update":"17.01.2022, 00:00 Uhr","additionalProperties":{},"sn_V2":null,"gen":"Berlin Neukölln","ags":null}},{"attributes":{"cases7_Per_100k":852.725124569785,"last_Update":"17.01.2022, 00:00 Uhr","additionalProperties":{},"sn_V2":null,"gen":"Berlin Lichtenberg","ags":null}},{"attributes":{"cases7_Per_100k":0.0,"last_Update":"17.01.2022, 00:00 Uhr","additionalProperties":{},"sn_V2":null,"gen":"Berlin Marzahn-Hellersdorf","ags":null}},{"attributes":{"cases7_Per_100k":954.990934687978,"last_Update":"17.01.2022, 00:00 Uhr","additionalProperties":{},"sn_V2":null,"gen":"Berlin Spandau","ags":null}},{"attributes":{"cases7_Per_100k":588.527482315057,"last_Update":"17.01.2022, 00:00 Uhr","additionalProperties":{},"sn_V2":null,"gen":"Berlin Steglitz-Zehlendorf","ags":null}},{"attributes":{"cases7_Per_100k":1351.91053470411,"last_Update":"17.01.2022, 00:00 Uhr","additionalProperties":{},"sn_V2":null,"gen":"Berlin Mitte","ags":null}},{"attributes":{"cases7_Per_100k":1596.28953117725,"last_Update":"17.01.2022, 00:00 Uhr","additionalProperties":{},"sn_V2":null,"gen":"Berlin Friedrichshain-Kreuzberg","ags":null}},{"attributes":{"cases7_Per_100k":818.644226712297,"last_Update":"17.01.2022, 00:00 Uhr","additionalProperties":{},"sn_V2":null,"gen":"Berlin Tempelhof-Schöneberg","ags":null}}],"additionalProperties":{}}